core/riscv/riscv_alu.v
//-----------------------------------------------------------------
//                         RISC-V Core
//                            V1.0.1
//                     Ultra-Embedded.com
//                     Copyright 2014-2019
//
//                   admin@ultra-embedded.com
//
//                       License: BSD
//-----------------------------------------------------------------
//
// Copyright (c) 2014-2019, Ultra-Embedded.com
// All rights reserved.
// 
// Redistribution and use in source and binary forms, with or without
// modification, are permitted provided that the following conditions 
// are met:
//   - Redistributions of source code must retain the above copyright
//     notice, this list of conditions and the following disclaimer.
//   - Redistributions in binary form must reproduce the above copyright
//     notice, this list of conditions and the following disclaimer 
//     in the documentation and/or other materials provided with the 
//     distribution.
//   - Neither the name of the author nor the names of its contributors 
//     may be used to endorse or promote products derived from this 
//     software without specific prior written permission.
// 
// THIS SOFTWARE IS PROVIDED BY THE COPYRIGHT HOLDERS AND CONTRIBUTORS 
// "AS IS" AND ANY EXPRESS OR IMPLIED WARRANTIES, INCLUDING, BUT NOT 
// LIMITED TO, THE IMPLIED WARRANTIES OF MERCHANTABILITY AND FITNESS FOR 
// A PARTICULAR PURPOSE ARE DISCLAIMED. IN NO EVENT SHALL THE AUTHOR BE 
// LIABLE FOR ANY DIRECT, INDIRECT, INCIDENTAL, SPECIAL, EXEMPLARY, OR 
// CONSEQUENTIAL DAMAGES (INCLUDING, BUT NOT LIMITED TO, PROCUREMENT OF 
// SUBSTITUTE GOODS OR SERVICES; LOSS OF USE, DATA, OR PROFITS; OR 
// BUSINESS INTERRUPTION) HOWEVER CAUSED AND ON ANY THEORY OF 
// LIABILITY, WHETHER IN CONTRACT, STRICT LIABILITY, OR TORT
// (INCLUDING NEGLIGENCE OR OTHERWISE) ARISING IN ANY WAY OUT OF 
// THE USE OF THIS SOFTWARE, EVEN IF ADVISED OF THE POSSIBILITY OF 
// SUCH DAMAGE.
//-----------------------------------------------------------------
module riscv_alu
(
    // Inputs
     input  [  3:0]  alu_op_i
    ,input  [ 31:0]  alu_a_i
    ,input  [ 31:0]  alu_b_i

    // Outputs
    ,output [ 31:0]  alu_p_o
);

//-----------------------------------------------------------------
// Includes
//-----------------------------------------------------------------
`include "riscv_defs.v"

//-----------------------------------------------------------------
// Registers
//-----------------------------------------------------------------
reg [31:0]      result_r;

reg [31:16]     shift_right_fill_r;
reg [31:0]      shift_right_1_r;
reg [31:0]      shift_right_2_r;
reg [31:0]      shift_right_4_r;
reg [31:0]      shift_right_8_r;

reg [31:0]      shift_left_1_r;
reg [31:0]      shift_left_2_r;
reg [31:0]      shift_left_4_r;
reg [31:0]      shift_left_8_r;

wire [31:0]     sub_res_w = alu_a_i - alu_b_i;

//-----------------------------------------------------------------
// ALU
//-----------------------------------------------------------------
always @ (alu_op_i or alu_a_i or alu_b_i or sub_res_w)
begin
    shift_right_fill_r = 16'b0;
    shift_right_1_r = 32'b0;
    shift_right_2_r = 32'b0;
    shift_right_4_r = 32'b0;
    shift_right_8_r = 32'b0;

    shift_left_1_r = 32'b0;
    shift_left_2_r = 32'b0;
    shift_left_4_r = 32'b0;
    shift_left_8_r = 32'b0;

    case (alu_op_i)
       //----------------------------------------------
       // Shift Left
       //----------------------------------------------   
       `ALU_SHIFTL :
       begin
        result_r = alu_a_i << alu_b_i[4:0];
       end
       //----------------------------------------------
       // Shift Right
       //----------------------------------------------
       `ALU_SHIFTR:
       begin
            result_r = alu_a_i >> alu_b_i[4:0];
       end
       `ALU_SHIFTR_ARITH:
       begin
            result_r = $signed(alu_a_i) >>> alu_b_i[4:0];
       end
       //----------------------------------------------
       // Arithmetic
       //----------------------------------------------
       `ALU_ADD : 
       begin
            result_r      = (alu_a_i + alu_b_i);
       end
       `ALU_SUB : 
       begin
            result_r      = sub_res_w;
       end
       //----------------------------------------------
       // Logical
       //----------------------------------------------       
       `ALU_AND : 
       begin
            result_r      = (alu_a_i & alu_b_i);
       end
       `ALU_OR  : 
       begin
            result_r      = (alu_a_i | alu_b_i);
       end
       `ALU_XOR : 
       begin
            result_r      = (alu_a_i ^ alu_b_i);
       end
       //----------------------------------------------
       // Comparision
       //----------------------------------------------
       `ALU_LESS_THAN : 
       begin
            result_r      = (alu_a_i < alu_b_i) ? 32'h1 : 32'h0;
       end
       `ALU_LESS_THAN_SIGNED : 
       begin
            if (alu_a_i[31] != alu_b_i[31])
                result_r  = alu_a_i[31] ? 32'h1 : 32'h0;
            else
                result_r  = sub_res_w[31] ? 32'h1 : 32'h0;            
       end       
       default  : 
       begin
            result_r      = alu_a_i;
       end
    endcase
end

assign alu_p_o    = result_r;

endmodule

testbench/alu/tb.v
`include "../../core/riscv/riscv_defs.v"
`include "../../core/riscv/riscv_alu.v"

module tb;
	reg signed [31:0] data_a;
	reg signed [31:0] data_b;
	reg [31:0] select;
	wire signed [31:0] result_y;

	riscv_alu dut (
		.alu_a_i(data_a),
		.alu_b_i(data_b),
		.alu_op_i(select[3:0]),
		.alu_p_o(result_y)
	);

	integer i;
	integer op_select;
	integer seed;
	initial begin
		seed = 123;
		$dumpfile("tb.vcd");
		$dumpvars(1, tb);

		for (i = 0; i < 50; i = i + 1) begin
			data_a = $random(seed);
			data_b = $random(seed);

			for (op_select = 0; op_select < 16; op_select = op_select + 1) begin
				select = op_select;
				#1;
			end
		end
		$finish;
	end
endmodule

testbench/alu/tb.vcd
$date
	Sat Sep 27 02:52:15 2025
$end
$version
	Icarus Verilog
$end
$timescale
	1s
$end
$scope module tb $end
$var wire 32 ! result_y [31:0] $end
$var reg 32 " data_a [31:0] $end
$var reg 32 # data_b [31:0] $end
$var reg 32 $ select [31:0] $end
$var integer 32 % i [31:0] $end
$var integer 32 & op_select [31:0] $end
$var integer 32 ' seed [31:0] $end
$upscope $end
$enddefinitions $end
$comment Show the parameter values. $end
$dumpall
$end
#0
$dumpvars
b10011110100000011101001110000001 '
b0 &
b0 %
b0 $
b11110100000011101010100111101 #
b10000000100000011010001000000001 "
b10000000100000011010001000000001 !
$end
#1
b100000000000000000000000000000 !
b1 $
b1 &
#2
b100 !
b10 $
b10 &
#3
b11111111111111111111111111111100 !
b11 $
b11 &
#4
b10011111000000110111011100111110 !
b100 $
b100 &
#5
b10000000100000011010001000000001 !
b101 $
b101 &
#6
b1100001111111111100110011000100 !
b110 $
b110 &
#7
b100000011000000000000001 !
b111 $
b111 &
#8
b10011110100000011111011100111101 !
b1000 $
b1000 &
#9
b10011110000000000111011100111100 !
b1001 $
b1001 &
#10
b0 !
b1010 $
b1010 &
#11
b1 !
b1011 $
b1011 &
#12
b10000000100000011010001000000001 !
b1100 $
b1100 &
#13
b1101 $
b1101 &
#14
b1110 $
b1110 &
#15
b1111 $
b1111 &
#16
b11011001001101001110110010110010 !
b0 $
b10001010101000010110010000010101 #
b11011001001101001110110010110010 "
b1010101000010110001101110111 '
b1 %
b0 &
#17
b10010110010000000000000000000000 !
b1 $
b1 &
#18
b11011001001 !
b10 $
b10 &
#19
b11111111111111111111111011001001 !
b11 $
b11 &
#20
b1100011110101100101000011000111 !
b100 $
b100 &
#21
b11011001001101001110110010110010 !
b101 $
b101 &
#22
b1001110100100111000100010011101 !
b110 $
b110 &
#23
b10001000001000000110010000010000 !
b111 $
b111 &
#24
b11011011101101011110110010110111 !
b1000 $
b1000 &
#25
b1010011100101011000100010100111 !
b1001 $
b1001 &
#26
b0 !
b1010 $
b1010 &
#27
b1011 $
b1011 &
#28
b11011001001101001110110010110010 !
b1100 $
b1100 &
#29
b1101 $
b1101 &
#30
b1110 $
b1110 &
#31
b1111 $
b1111 &
#32
b10011000110000001011001000110001 !
b0 $
b11001100100110101101011010011001 #
b10011000110000001011001000110001 "
b1001100100110101101010111011101 '
b10 %
b0 &
#33
b1100010000000000000000000000000 !
b1 $
b1 &
#34
b1001100 !
b10 $
b10 &
#35
b11111111111111111111111111001100 !
b11 $
b11 &
#36
b1100101010110111000100011001010 !
b100 $
b100 &
#37
b10011000110000001011001000110001 !
b101 $
b101 &
#38
b11001100001001011101101110011000 !
b110 $
b110 &
#39
b10001000100000001001001000010001 !
b111 $
b111 &
#40
b11011100110110101111011010111001 !
b1000 $
b1000 &
#41
b1010100010110100110010010101000 !
b1001 $
b1001 &
#42
b1 !
b1010 $
b1010 &
#43
b1011 $
b1011 &
#44
b10011000110000001011001000110001 !
b1100 $
b1100 &
#45
b1101 $
b1101 &
#46
b1110 $
b1110 &
#47
b1111 $
b1111 &
#48
b10001010101101100111110000010101 !
b0 $
b11010011010110010010111010100110 #
b10001010101101100111110000010101 "
b1010011010110010010110000110011 '
b11 %
b0 &
#49
b10101101100111110000010101000000 !
b1 $
b1 &
#50
b10001010101101100111110000 !
b10 $
b10 &
#51
b11111110001010101101100111110000 !
b11 $
b11 &
#52
b1011110000011111010101010111011 !
b100 $
b100 &
#53
b10001010101101100111110000010101 !
b101 $
b101 &
#54
b10110111010111010100110101101111 !
b110 $
b110 &
#55
b10000010000100000010110000000100 !
b111 $
b111 &
#56
b11011011111111110111111010110111 !
b1000 $
b1000 &
#57
b1011001111011110101001010110011 !
b1001 $
b1001 &
#58
b1 !
b1010 $
b1010 &
#59
b1011 $
b1011 &
#60
b10001010101101100111110000010101 !
b1100 $
b1100 &
#61
b1101 $
b1101 &
#62
b1110 $
b1110 &
#63
b1111 $
b1111 &
#64
b11110001110110011111110011100011 !
b0 $
b10111001001100001010010001110010 #
b11110001110110011111110011100011 "
b111001001100001010001111111001 '
b100 %
b0 &
#65
b11110011100011000000000000000000 !
b1 $
b1 &
#66
b11110001110110 !
b10 $
b10 &
#67
b11111111111111111111110001110110 !
b11 $
b11 &
#68
b10101011000010101010000101010101 !
b100 $
b100 &
#69
b11110001110110011111110011100011 !
b101 $
b101 &
#70
b111000101010010101100001110001 !
b110 $
b110 &
#71
b10110001000100001010010001100010 !
b111 $
b111 &
#72
b11111001111110011111110011110011 !
b1000 $
b1000 &
#73
b1001000111010010101100010010001 !
b1001 $
b1001 &
#74
b0 !
b1010 $
b1010 &
#75
b1011 $
b1011 &
#76
b11110001110110011111110011100011 !
b1100 $
b1100 &
#77
b1101 $
b1101 &
#78
b1110 $
b1110 &
#79
b1111 $
b1111 &
#80
b1101000001111111111010111010000 !
b0 $
b10101101111110000001100001011011 #
b1101000001111111111010111010000 "
b101101111110000001011010101111 '
b101 %
b0 &
#81
b10000000000000000000000000000000 !
b1 $
b1 &
#82
b1101 !
b10 $
b10 &
#83
b11 $
b11 &
#84
b10110001110000000111000101011 !
b100 $
b100 &
#85
b1101000001111111111010111010000 !
b101 $
b101 &
#86
b10111010010001111101110101110101 !
b110 $
b110 &
#87
b101000001110000001000001010000 !
b111 $
b111 &
#88
b11101101111111111111110111011011 !
b1000 $
b1000 &
#89
b11000101110001111110110110001011 !
b1001 $
b1001 &
#90
b1 !
b1010 $
b1010 &
#91
b0 !
b1011 $
b1011 &
#92
b1101000001111111111010111010000 !
b1100 $
b1100 &
#93
b1101 $
b1101 &
#94
b1110 $
b1110 &
#95
b1111 $
b1111 &
#96
b11111111100000000000111011111111 !
b0 $
b100111010110010101101101001110 #
b11111111100000000000111011111111 "
b10100111010110010101100111010101 '
b110 %
b0 &
#97
b11101111111100000000000000 !
b1 $
b1 &
#98
b111111111000000000 !
b10 $
b10 &
#99
b11111111111111111111111000000000 !
b11 $
b11 &
#100
b100110110110010110101001001101 !
b100 $
b100 &
#101
b11111111100000000000111011111111 !
b101 $
b101 &
#102
b11011000001001101011001110110001 !
b110 $
b110 &
#103
b100111000000000000101001001110 !
b111 $
b111 &
#104
b11111111110110010101111111111111 !
b1000 $
b1000 &
#105
b11011000110110010101010110110001 !
b1001 $
b1001 &
#106
b0 !
b1010 $
b1010 &
#107
b1 !
b1011 $
b1011 &
#108
b11111111100000000000111011111111 !
b1100 $
b1100 &
#109
b1101 $
b1101 &
#110
b1110 $
b1110 &
#111
b1111 $
b1111 &
#112
b1100101111100011100001111001011 !
b0 $
b10101001111100001010000001010011 #
b1100101111100011100001111001011 "
b101001111100001001111011101011 '
b111 %
b0 &
#113
b11110010110000000000000000000 !
b1 $
b1 &
#114
b110010111110 !
b10 $
b10 &
#115
b11 $
b11 &
#116
b1111111000100110010000011110 !
b100 $
b100 &
#117
b1100101111100011100001111001011 !
b101 $
b101 &
#118
b10111100000000010010001101111000 !
b110 $
b110 &
#119
b100001111100001000000001000011 !
b111 $
b111 &
#120
b11101101111100011110001111011011 !
b1000 $
b1000 &
#121
b11001100000000010110001110011000 !
b1001 $
b1001 &
#122
b1 !
b1010 $
b1010 &
#123
b0 !
b1011 $
b1011 &
#124
b1100101111100011100001111001011 !
b1100 $
b1100 &
#125
b1101 $
b1101 &
#126
b1110 $
b1110 &
#127
b1111 $
b1111 &
#128
b11101100101011000011001011011001 !
b0 $
b1110101100100101101010111101011 #
b11101100101011000011001011011001 "
b11110101100100101101001101110001 '
b1000 %
b0 &
#129
b1100001100101101100100000000000 !
b1 $
b1 &
#130
b111011001010110000110 !
b10 $
b10 &
#131
b11111111111111011001010110000110 !
b11 $
b11 &
#132
b1100010001111110000100011000100 !
b100 $
b100 &
#133
b11101100101011000011001011011001 !
b101 $
b101 &
#134
b1110111000110010101110011101110 !
b110 $
b110 &
#135
b1100100100000000001000011001001 !
b111 $
b111 &
#136
b11111101101111101111011111111011 !
b1000 $
b1000 &
#137
b10011001001111101110011100110010 !
b1001 $
b1001 &
#138
b0 !
b1010 $
b1010 &
#139
b1 !
b1011 $
b1011 &
#140
b11101100101011000011001011011001 !
b1100 $
b1100 &
#141
b1101 $
b1101 &
#142
b1110 $
b1110 &
#143
b1111 $
b1111 &
#144
b1101110110000010001000111011101 !
b0 $
b10001100110100110000001000011001 #
b1101110110000010001000111011101 "
b1100110100110000000011100111 '
b1001 %
b0 &
#145
b10111010000000000000000000000000 !
b1 $
b1 &
#146
b110111 !
b10 $
b10 &
#147
b11 $
b11 &
#148
b11111011100101000001001111110110 !
b100 $
b100 &
#149
b1101110110000010001000111011101 !
b101 $
b101 &
#150
b11100001111011100000111111000100 !
b110 $
b110 &
#151
b1100110000010000000000011001 !
b111 $
b111 &
#152
b11101110110100110001001111011101 !
b1000 $
b1000 &
#153
b11100010000100100001001111000100 !
b1001 $
b1001 &
#154
b1 !
b1010 $
b1010 &
#155
b0 !
b1011 $
b1011 &
#156
b1101110110000010001000111011101 !
b1100 $
b1100 &
#157
b1101 $
b1101 &
#158
b1110 $
b1110 &
#159
b1111 $
b1111 &
#160
b1111100111010100111010111111001 !
b0 $
b1100011100111101010111111000111 #
b1111100111010100111010111111001 "
b11100011100111101010110011001101 '
b1010 %
b0 &
#161
b1110101001110101111110010000000 !
b1 $
b1 &
#162
b111110011101010011101011 !
b10 $
b10 &
#163
b11 $
b11 &
#164
b11100000100010010010010111000000 !
b100 $
b100 &
#165
b1111100111010100111010111111001 !
b101 $
b101 &
#166
b11001010010111100011000110010 !
b110 $
b110 &
#167
b1100000100010100010010111000001 !
b111 $
b111 &
#168
b1111111111111101111111111111111 !
b1000 $
b1000 &
#169
b11111011101001101101000111110 !
b1001 $
b1001 &
#170
b0 !
b1010 $
b1010 &
#171
b1011 $
b1011 &
#172
b1111100111010100111010111111001 !
b1100 $
b1100 &
#173
b1101 $
b1101 &
#174
b1110 $
b1110 &
#175
b1111 $
b1111 &
#176
b10000001101000111100101000000011 !
b0 $
b11101010100010010011101011010101 #
b10000001101000111100101000000011 "
b1101010100010010011100010100011 '
b1011 %
b0 &
#177
b1000000011000000000000000000000 !
b1 $
b1 &
#178
b10000001101 !
b10 $
b10 &
#179
b11111111111111111111110000001101 !
b11 $
b11 &
#180
b1101100001011010000010011011000 !
b100 $
b100 &
#181
b10000001101000111100101000000011 !
b101 $
b101 &
#182
b10010111000110101000111100101110 !
b110 $
b110 &
#183
b10000000100000010000101000000001 !
b111 $
b111 &
#184
b11101011101010111111101011010111 !
b1000 $
b1000 &
#185
b1101011001010101111000011010110 !
b1001 $
b1001 &
#186
b1 !
b1010 $
b1010 &
#187
b1011 $
b1011 &
#188
b10000001101000111100101000000011 !
b1100 $
b1100 &
#189
b1101 $
b1101 &
#190
b1110 $
b1110 &
#191
b1111 $
b1111 &
#192
b11001011010001100000000 !
b0 $
b11100000111100100001100111000 #
b11001011010001100000000 "
b10011100000111100100000111101001 '
b1100 %
b0 &
#193
b0 !
b1 $
b1 &
#194
b10 $
b10 &
#195
b11 $
b11 &
#196
b11100100000111110011000111000 !
b100 $
b100 &
#197
b11001011010001100000000 !
b101 $
b101 &
#198
b11100100010001110101111111001000 !
b110 $
b110 &
#199
b1000000001100000000 !
b111 $
b111 &
#200
b11100011111111110001100111000 !
b1000 $
b1000 &
#201
b11100011110111110000000111000 !
b1001 $
b1001 &
#202
b1 !
b1010 $
b1010 &
#203
b1011 $
b1011 &
#204
b11001011010001100000000 !
b1100 $
b1100 &
#205
b1101 $
b1101 &
#206
b1110 $
b1110 &
#207
b1111 $
b1111 &
#208
b1001111011111001001111110011110 !
b0 $
b10010111010100110000010000101110 #
b1001111011111001001111110011110 "
b10111010100110000001000011111 '
b1101 %
b0 &
#209
b100111111001111000000000000000 !
b1 $
b1 &
#210
b10011110111110010 !
b10 $
b10 &
#211
b11 $
b11 &
#212
b11100110110011111010001111001100 !
b100 $
b100 &
#213
b1001111011111001001111110011110 !
b101 $
b101 &
#214
b10111000001010011001101101110000 !
b110 $
b110 &
#215
b111010100000000010000001110 !
b111 $
b111 &
#216
b11011111011111111001111110111110 !
b1000 $
b1000 &
#217
b11011000001011111001101110110000 !
b1001 $
b1001 &
#218
b1 !
b1010 $
b1010 &
#219
b0 !
b1011 $
b1011 &
#220
b1001111011111001001111110011110 !
b1100 $
b1100 &
#221
b1101 $
b1101 &
#222
b1110 $
b1110 &
#223
b1111 $
b1111 &
#224
b1100110101100110100011111001101 !
b0 $
b10011101111011101011000000111011 #
b1100110101100110100011111001101 "
b11101111011101010111011000101 '
b1110 %
b0 &
#225
b1101000000000000000000000000000 !
b1 $
b1 &
#226
b1100 !
b10 $
b10 &
#227
b11 $
b11 &
#228
b100101000011111100000001000 !
b100 $
b100 &
#229
b1100110101100110100011111001101 !
b101 $
b101 &
#230
b11001000110001001001011110010010 !
b110 $
b110 &
#231
b100101000100000000000001001 !
b111 $
b111 &
#232
b11111111111111111111011111111111 !
b1000 $
b1000 &
#233
b11111011010111011111011111110110 !
b1001 $
b1001 &
#234
b1 !
b1010 $
b1010 &
#235
b0 !
b1011 $
b1011 &
#236
b1100110101100110100011111001101 !
b1100 $
b1100 &
#237
b1101 $
b1101 &
#238
b1110 $
b1110 &
#239
b1111 $
b1111 &
#240
b1000101110001101111011110001011 !
b0 $
b11101111100000011101101011011111 #
b1000101110001101111011110001011 "
b1101111100000011101100101011011 '
b1111 %
b0 &
#241
b10000000000000000000000000000000 !
b1 $
b1 &
#242
b0 !
b10 $
b10 &
#243
b11 $
b11 &
#244
b110101010010001101001001101010 !
b100 $
b100 &
#245
b1000101110001101111011110001011 !
b101 $
b101 &
#246
b1010110010001010001110010101100 !
b110 $
b110 &
#247
b1000101100000001101001010001011 !
b111 $
b111 &
#248
b11101111110001111111111111011111 !
b1000 $
b1000 &
#249
b10101010010001110010110101010100 !
b1001 $
b1001 &
#250
b1 !
b1010 $
b1010 &
#251
b0 !
b1011 $
b1011 &
#252
b1000101110001101111011110001011 !
b1100 $
b1100 &
#253
b1101 $
b1101 &
#254
b1110 $
b1110 &
#255
b1111 $
b1111 &
#256
b111100010111111010111101111000 !
b0 $
b11100001010001001101000011000010 #
b111100010111111010111101111000 "
b1100001010001001100111101100001 '
b10000 %
b0 &
#257
b11110001011111101011110111100000 !
b1 $
b1 &
#258
b1111000101111110101111011110 !
b10 $
b10 &
#259
b11 $
b11 &
#260
b11101101001001000000000111010 !
b100 $
b100 &
#261
b111100010111111010111101111000 !
b101 $
b101 &
#262
b1011011000110101101111010110110 !
b110 $
b110 &
#263
b100000010001001000000001000000 !
b111 $
b111 &
#264
b11111101010111111111111111111010 !
b1000 $
b1000 &
#265
b11011101000110110111111110111010 !
b1001 $
b1001 &
#266
b1 !
b1010 $
b1010 &
#267
b0 !
b1011 $
b1011 &
#268
b111100010111111010111101111000 !
b1100 $
b1100 &
#269
b1101 $
b1101 &
#270
b1110 $
b1110 &
#271
b1111 $
b1111 &
#272
b10110010000000101111111001100100 !
b0 $
b10110000111101001111110001100001 #
b10110010000000101111111001100100 "
b110000111101001111101001010111 '
b10001 %
b0 &
#273
b1100100000001011111110011001000 !
b1 $
b1 &
#274
b1011001000000010111111100110010 !
b10 $
b10 &
#275
b11011001000000010111111100110010 !
b11 $
b11 &
#276
b1100010111101111111101011000101 !
b100 $
b100 &
#277
b10110010000000101111111001100100 !
b101 $
b101 &
#278
b1000011100000001000000011 !
b110 $
b110 &
#279
b10110000000000001111110001100000 !
b111 $
b111 &
#280
b10110010111101101111111001100101 !
b1000 $
b1000 &
#281
b10111101100000001000000101 !
b1001 $
b1001 &
#282
b0 !
b1010 $
b1010 &
#283
b1011 $
b1011 &
#284
b10110010000000101111111001100100 !
b1100 $
b1100 &
#285
b1101 $
b1101 &
#286
b1110 $
b1110 &
#287
b1111 $
b1111 &
#288
b11111001110011110010100111110 !
b0 $
b11010100100010010100000010101001 #
b11111001110011110010100111110 "
b1010100100010010011111110111101 '
b10010 %
b0 &
#289
b1110011110010100111110000000000 !
b1 $
b1 &
#290
b11111001110011110010 !
b10 $
b10 &
#291
b11 $
b11 &
#292
b11110011110000110010010111100111 !
b100 $
b100 &
#293
b11111001110011110010100111110 !
b101 $
b101 &
#294
b1001010101100001010010010010101 !
b110 $
b110 &
#295
b10100000010010100000000101000 !
b111 $
b111 &
#296
b11011111101110011110010110111111 !
b1000 $
b1000 &
#297
b11001011101100001010010110010111 !
b1001 $
b1001 &
#298
b1 !
b1010 $
b1010 &
#299
b0 !
b1011 $
b1011 &
#300
b11111001110011110010100111110 !
b1100 $
b1100 &
#301
b1101 $
b1101 &
#302
b1110 $
b1110 &
#303
b1111 $
b1111 &
#304
b1101001111000011010010111010011 !
b0 $
b11100010010101010110001011000100 #
b1101001111000011010010111010011 "
b1100010010101010110000100010011 '
b10011 %
b0 &
#305
b10011110000110100101110100110000 !
b1 $
b1 &
#306
b110100111100001101001011101 !
b10 $
b10 &
#307
b11 $
b11 &
#308
b1001100001101110000100010010111 !
b100 $
b100 &
#309
b1101001111000011010010111010011 !
b101 $
b101 &
#310
b10000111100011000100001100001111 !
b110 $
b110 &
#311
b1100000010000010010000011000000 !
b111 $
b111 &
#312
b11101011111101011110011111010111 !
b1000 $
b1000 &
#313
b10001011101101001100011100010111 !
b1001 $
b1001 &
#314
b1 !
b1010 $
b1010 &
#315
b0 !
b1011 $
b1011 &
#316
b1101001111000011010010111010011 !
b1100 $
b1100 &
#317
b1101 $
b1101 &
#318
b1110 $
b1110 &
#319
b1111 $
b1111 &
#320
b11110101010111111011010011101010 !
b0 $
b1100111101000101110100011001 #
b11110101010111111011010011101010 "
b10001100111101000101101111011001 '
b10100 %
b0 &
#321
b11010100000000000000000000000000 !
b1 $
b1 &
#322
b1111010 !
b10 $
b10 &
#323
b11111111111111111111111111111010 !
b11 $
b11 &
#324
b10010101000001001000000011 !
b100 $
b100 &
#325
b11110101010111111011010011101010 !
b101 $
b101 &
#326
b11101000011010110101011111010001 !
b110 $
b110 &
#327
b100010101000001010000001000 !
b111 $
b111 &
#328
b11111101111111111111110111111011 !
b1000 $
b1000 &
#329
b11111001101010111110100111110011 !
b1001 $
b1001 &
#330
b0 !
b1010 $
b1010 &
#331
b1 !
b1011 $
b1011 &
#332
b11110101010111111011010011101010 !
b1100 $
b1100 &
#333
b1101 $
b1101 &
#334
b1110 $
b1110 &
#335
b1111 $
b1111 &
#336
b100100001100001001001101001000 !
b0 $
b100000100011100101100001000 #
b100100001100001001001101001000 "
b10000100000100011100100110001111 '
b10101 %
b0 &
#337
b110000100100110100100000000000 !
b1 $
b1 &
#338
b1001000011000010010011 !
b10 $
b10 &
#339
b11 $
b11 &
#340
b101000010000100101111001010000 !
b100 $
b100 &
#341
b100100001100001001001101001000 !
b101 $
b101 &
#342
b100000000111101100100001000000 !
b110 $
b110 &
#343
b100000100001000001100001000 !
b111 $
b111 &
#344
b100100001100011101101101001000 !
b1000 $
b1000 &
#345
b100000001000010101100001000000 !
b1001 $
b1001 &
#346
b0 !
b1010 $
b1010 &
#347
b1011 $
b1011 &
#348
b100100001100001001001101001000 !
b1100 $
b1100 &
#349
b1101 $
b1101 &
#350
b1110 $
b1110 &
#351
b1111 $
b1111 &
#352
b11110011000010011010110011100110 !
b0 $
b11000110111010100100000010001101 #
b11110011000010011010110011100110 "
b1000110111010100011111110110101 '
b10110 %
b0 &
#353
b110101100111001100000000000000 !
b1 $
b1 &
#354
b1111001100001001101 !
b10 $
b10 &
#355
b11111111111111111001100001001101 !
b11 $
b11 &
#356
b10111001111100111110110101110011 !
b100 $
b100 &
#357
b11110011000010011010110011100110 !
b101 $
b101 &
#358
b101100000111110110110001011001 !
b110 $
b110 &
#359
b11000010000010000000000010000100 !
b111 $
b111 &
#360
b11110111111010111110110011101111 !
b1000 $
b1000 &
#361
b110101111000111110110001101011 !
b1001 $
b1001 &
#362
b0 !
b1010 $
b1010 &
#363
b1011 $
b1011 &
#364
b11110011000010011010110011100110 !
b1100 $
b1100 &
#365
b1101 $
b1101 &
#366
b1110 $
b1110 &
#367
b1111 $
b1111 &
#368
b1101110100001100011011111011101 !
b0 $
b10000111000110101011000000001110 #
b1101110100001100011011111011101 "
b111000110101010111111001011 '
b10111 %
b0 &
#369
b10001101111101110100000000000000 !
b1 $
b1 &
#370
b11011101000011000 !
b10 $
b10 &
#371
b11 $
b11 &
#372
b11110101101000001110011111101011 !
b100 $
b100 &
#373
b1101110100001100011011111011101 !
b101 $
b101 &
#374
b11100111011010111000011111001111 !
b110 $
b110 &
#375
b110000000100011000000001100 !
b111 $
b111 &
#376
b11101111100111101011011111011111 !
b1000 $
b1000 &
#377
b11101001100111001000011111010011 !
b1001 $
b1001 &
#378
b1 !
b1010 $
b1010 &
#379
b0 !
b1011 $
b1011 &
#380
b1101110100001100011011111011101 !
b1100 $
b1100 &
#381
b1101 $
b1101 &
#382
b1110 $
b1110 &
#383
b1111 $
b1111 &
#384
b111011000101110001011101110110 !
b0 $
b10010010000101101100100000100100 #
b111011000101110001011101110110 "
b10010000101101100011101010001 '
b11000 %
b0 &
#385
b10110001011100010111011101100000 !
b1 $
b1 &
#386
b11101100010111000101110111 !
b10 $
b10 &
#387
b11 $
b11 &
#388
b11001101001011011101111110011010 !
b100 $
b100 &
#389
b111011000101110001011101110110 !
b101 $
b101 &
#390
b10101001000000000100111101010010 !
b110 $
b110 &
#391
b10010000101100000000000100100 !
b111 $
b111 &
#392
b10111011000101111101111101110110 !
b1000 $
b1000 &
#393
b10101001000000011101111101010010 !
b1001 $
b1001 &
#394
b1 !
b1010 $
b1010 &
#395
b0 !
b1011 $
b1011 &
#396
b111011000101110001011101110110 !
b1100 $
b1100 &
#397
b1101 $
b1101 &
#398
b1110 $
b1110 &
#399
b1111 $
b1111 &
#400
b11101011101011011011101011010111 !
b0 $
b1000101010111100101000110001010 #
b11101011101011011011101011010111 "
b11000101010111100100111111000111 '
b11001 %
b0 &
#401
b10110110111010110101110000000000 !
b1 $
b1 &
#402
b1110101110101101101110 !
b10 $
b10 &
#403
b11111111111110101110101101101110 !
b11 $
b11 &
#404
b110001000011000000110001100001 !
b100 $
b100 &
#405
b11101011101011011011101011010111 !
b101 $
b101 &
#406
b10100110010011110110100101001101 !
b110 $
b110 &
#407
b1000001000011000001000010000010 !
b111 $
b111 &
#408
b11101111111111111111101111011111 !
b1000 $
b1000 &
#409
b10101110111100111110101101011101 !
b1001 $
b1001 &
#410
b0 !
b1010 $
b1010 &
#411
b1 !
b1011 $
b1011 &
#412
b11101011101011011011101011010111 !
b1100 $
b1100 &
#413
b1101 $
b1101 &
#414
b1110 $
b1110 &
#415
b1111 $
b1111 &
#416
b10100110010110011111111001001100 !
b0 $
b11000101010010011001000010001010 #
b10100110010110011111111001001100 "
b1000101010010011000111010101101 '
b11010 %
b0 &
#417
b1100111111110010011000000000000 !
b1 $
b1 &
#418
b1010011001011001111111 !
b10 $
b10 &
#419
b11111111111010011001011001111111 !
b11 $
b11 &
#420
b1101011101000111000111011010110 !
b100 $
b100 &
#421
b10100110010110011111111001001100 !
b101 $
b101 &
#422
b11100001000100000110110111000010 !
b110 $
b110 &
#423
b10000100010010011001000000001000 !
b111 $
b111 &
#424
b11100111010110011111111011001110 !
b1000 $
b1000 &
#425
b1100011000100000110111011000110 !
b1001 $
b1001 &
#426
b1 !
b1010 $
b1010 &
#427
b1011 $
b1011 &
#428
b10100110010110011111111001001100 !
b1100 $
b1100 &
#429
b1101 $
b1101 &
#430
b1110 $
b1110 &
#431
b1111 $
b1111 &
#432
b1000110110100110000101110001101 !
b0 $
b1111000000001001010011111110000 #
b1000110110100110000101110001101 "
b11111000000001001010010110000011 '
b11011 %
b0 &
#433
b1011100011010000000000000000 !
b1 $
b1 &
#434
b100011011010011 !
b10 $
b10 &
#435
b11 $
b11 &
#436
b10111110110101111011001101111101 !
b100 $
b100 &
#437
b1000110110100110000101110001101 !
b101 $
b101 &
#438
b11001110110011100110001110011101 !
b110 $
b110 &
#439
b1000000000000000000001110000000 !
b111 $
b111 &
#440
b1111110110101111010111111111101 !
b1000 $
b1000 &
#441
b111110110101111010110001111101 !
b1001 $
b1001 &
#442
b1 !
b1010 $
b1010 &
#443
b1011 $
b1011 &
#444
b1000110110100110000101110001101 !
b1100 $
b1100 &
#445
b1101 $
b1101 &
#446
b1110 $
b1110 &
#447
b1111 $
b1111 &
