core/riscv/riscv_divider.v
//-----------------------------------------------------------------
//                         RISC-V Core
//                            V1.0.1
//                     Ultra-Embedded.com
//                     Copyright 2014-2019
//
//                   admin@ultra-embedded.com
//
//                       License: BSD
//-----------------------------------------------------------------
//
// Copyright (c) 2014-2019, Ultra-Embedded.com
// All rights reserved.
// 
// Redistribution and use in source and binary forms, with or without
// modification, are permitted provided that the following conditions 
// are met:
//   - Redistributions of source code must retain the above copyright
//     notice, this list of conditions and the following disclaimer.
//   - Redistributions in binary form must reproduce the above copyright
//     notice, this list of conditions and the following disclaimer 
//     in the documentation and/or other materials provided with the 
//     distribution.
//   - Neither the name of the author nor the names of its contributors 
//     may be used to endorse or promote products derived from this 
//     software without specific prior written permission.
// 
// THIS SOFTWARE IS PROVIDED BY THE COPYRIGHT HOLDERS AND CONTRIBUTORS 
// "AS IS" AND ANY EXPRESS OR IMPLIED WARRANTIES, INCLUDING, BUT NOT 
// LIMITED TO, THE IMPLIED WARRANTIES OF MERCHANTABILITY AND FITNESS FOR 
// A PARTICULAR PURPOSE ARE DISCLAIMED. IN NO EVENT SHALL THE AUTHOR BE 
// LIABLE FOR ANY DIRECT, INDIRECT, INCIDENTAL, SPECIAL, EXEMPLARY, OR 
// CONSEQUENTIAL DAMAGES (INCLUDING, BUT NOT LIMITED TO, PROCUREMENT OF 
// SUBSTITUTE GOODS OR SERVICES; LOSS OF USE, DATA, OR PROFITS; OR 
// BUSINESS INTERRUPTION) HOWEVER CAUSED AND ON ANY THEORY OF 
// LIABILITY, WHETHER IN CONTRACT, STRICT LIABILITY, OR TORT
// (INCLUDING NEGLIGENCE OR OTHERWISE) ARISING IN ANY WAY OUT OF 
// THE USE OF THIS SOFTWARE, EVEN IF ADVISED OF THE POSSIBILITY OF 
// SUCH DAMAGE.
//-----------------------------------------------------------------

module riscv_divider
(
    // Inputs
     input           clk_i
    ,input           rst_i
    ,input           opcode_valid_i
    ,input  [ 31:0]  opcode_opcode_i
    ,input  [ 31:0]  opcode_pc_i
    ,input           opcode_invalid_i
    ,input  [  4:0]  opcode_rd_idx_i
    ,input  [  4:0]  opcode_ra_idx_i
    ,input  [  4:0]  opcode_rb_idx_i
    ,input  [ 31:0]  opcode_ra_operand_i
    ,input  [ 31:0]  opcode_rb_operand_i

    // Outputs
    ,output          writeback_valid_o
    ,output [ 31:0]  writeback_value_o
);



//-----------------------------------------------------------------
// Includes
//-----------------------------------------------------------------
`include "riscv_defs.v"

// Stage 1

reg [31:0] opcode_ra_operand_q_s1;
reg [31:0] opcode_rb_operand_q_s1;
reg valid_q_s1;
reg [31:0] opcode_opcode_q_s1;

always @ (posedge clk_i or posedge rst_i) begin
    if (rst_i) begin
        opcode_ra_operand_q_s1 <= 0;
        opcode_rb_operand_q_s1 <= 0;
        valid_q_s1 <= 0;
        opcode_opcode_q_s1 <= 0;
    end else begin
        valid_q_s1 <= opcode_valid_i;
        opcode_ra_operand_q_s1 <= opcode_ra_operand_i;
        opcode_rb_operand_q_s1 <= opcode_rb_operand_i;
        opcode_opcode_q_s1 <= opcode_opcode_i;
    end
end

// Stage 2

reg          valid_q;
reg  [31:0]  wb_result_q;

wire div_rem_inst_w     = ((opcode_opcode_q_s1 & `INST_DIV_MASK) == `INST_DIV)  || 
                          ((opcode_opcode_q_s1 & `INST_DIVU_MASK) == `INST_DIVU) ||
                          ((opcode_opcode_q_s1 & `INST_REM_MASK) == `INST_REM)  ||
                          ((opcode_opcode_q_s1 & `INST_REMU_MASK) == `INST_REMU);

wire signed_operation_w = ((opcode_opcode_q_s1 & `INST_DIV_MASK) == `INST_DIV) || ((opcode_opcode_q_s1 & `INST_REM_MASK) == `INST_REM);
wire div_operation_w    = ((opcode_opcode_q_s1 & `INST_DIV_MASK) == `INST_DIV) || ((opcode_opcode_q_s1 & `INST_DIVU_MASK) == `INST_DIVU);

always @ (posedge clk_i or posedge rst_i) begin
    if (rst_i) begin
        valid_q <= 0;
        wb_result_q <= 0;
    end else if (div_rem_inst_w) begin
        valid_q <= valid_q_s1 && div_rem_inst_w;
        if (div_operation_w) begin
            if (signed_operation_w) begin
                wb_result_q <= $signed(opcode_ra_operand_q_s1) / $signed(opcode_rb_operand_q_s1);
            end else begin
                wb_result_q <= $unsigned(opcode_ra_operand_q_s1) / $unsigned(opcode_rb_operand_q_s1);
            end
        end else begin
            if (signed_operation_w) begin
                wb_result_q <= $signed(opcode_ra_operand_q_s1) % $signed(opcode_rb_operand_q_s1);
            end else begin
                wb_result_q <= $unsigned(opcode_ra_operand_q_s1) % $unsigned(opcode_rb_operand_q_s1);
            end
        end
    end
end

assign writeback_valid_o = valid_q;
assign writeback_value_o = wb_result_q;



endmodule

testbench/divider/divider_tb.v
`include "../../core/riscv/riscv_defs.v"
`include "../../core/riscv/riscv_divider.v"

module tb;
	reg           clk_i;
	reg           rst_i;
	reg           opcode_valid_i;
	reg  [ 31:0]  opcode_opcode_i;
	reg  [ 31:0]  opcode_pc_i;
	reg           opcode_invalid_i;
	reg  [  4:0]  opcode_rd_idx_i;
	reg  [  4:0]  opcode_ra_idx_i;
	reg  [  4:0]  opcode_rb_idx_i;
	reg  [ 31:0]  opcode_ra_operand_i;
	reg  [ 31:0]  opcode_rb_operand_i;
	wire          writeback_valid_o;
	wire [ 31:0]  writeback_value_o;

	riscv_divider dut (
		.clk_i(clk_i),
		.rst_i(rst_i),
		.opcode_valid_i(opcode_valid_i),
		.opcode_opcode_i(opcode_opcode_i),
		.opcode_pc_i(opcode_pc_i),
		.opcode_invalid_i(opcode_invalid_i),
		.opcode_rd_idx_i(opcode_rd_idx_i),
		.opcode_ra_idx_i(opcode_ra_idx_i),
		.opcode_rb_idx_i(opcode_rb_idx_i),
		.opcode_ra_operand_i(opcode_ra_operand_i),
		.opcode_rb_operand_i(opcode_rb_operand_i),
		.writeback_valid_o(writeback_valid_o),
		.writeback_value_o(writeback_value_o)
	);

	integer seed;
	integer i;

	initial begin
		$dumpfile(".divider_tb.vcd");
		$dumpvars(1, tb);

		clk_i = 0;
		rst_i = 1;
		opcode_valid_i = 0;
		opcode_opcode_i = 0;
		opcode_pc_i = 0;
		opcode_invalid_i = 0;
		opcode_rd_idx_i = 0;
		opcode_ra_idx_i = 0;
		opcode_rb_idx_i = 0;
		opcode_ra_operand_i = 0;
		opcode_rb_operand_i = 0;
		#1;
		for (i = 0; i < 1000; i += 1) begin
			clk_i = !clk_i;
			#1;
		end
	end

endmodule

testbench/divider/.divider_tb.vcd
$date
	Sun Nov  2 01:53:40 2025
$end
$version
	Icarus Verilog
$end
$timescale
	1s
$end
$scope module tb $end
$var wire 32 ! writeback_value_o [31:0] $end
$var wire 1 " writeback_valid_o $end
$var reg 1 # clk_i $end
$var reg 1 $ opcode_invalid_i $end
$var reg 32 % opcode_opcode_i [31:0] $end
$var reg 32 & opcode_pc_i [31:0] $end
$var reg 5 ' opcode_ra_idx_i [4:0] $end
$var reg 32 ( opcode_ra_operand_i [31:0] $end
$var reg 5 ) opcode_rb_idx_i [4:0] $end
$var reg 32 * opcode_rb_operand_i [31:0] $end
$var reg 5 + opcode_rd_idx_i [4:0] $end
$var reg 1 , opcode_valid_i $end
$var reg 1 - rst_i $end
$var integer 32 . i [31:0] $end
$var integer 32 / seed [31:0] $end
$upscope $end
$enddefinitions $end
$comment Show the parameter values. $end
$dumpall
$end
#0
$dumpvars
bx /
bx .
1-
0,
b0 +
b0 *
b0 )
b0 (
b0 '
b0 &
b0 %
0$
0#
0"
b0 !
$end
#1
b11000000100010010101111010000001 *
b10010000101010011010100100100 (
b1000000100010010101110011001111 /
b10000000000100000000110011 %
b0 .
1,
0-
#2
bx !
1#
#3
b10110001111100000101011001100011 *
b10000100100001001101011000001001 (
b110001111100000101010011110101 /
0#
b10000000000101000000110011 %
b1 .
#4
b0 !
1"
1#
#5
b1000110110111111001100110001101 *
b110101110010111101100001101 (
b11000110110111111001011100001011 /
0#
b10000000000110000000110011 %
b10 .
#6
1#
#7
b10001001001101110101001000010010 *
b10110010110000101000010001100101 (
b1001001101110101000010010001 /
0#
b10000000000111000000110011 %
b11 .
#8
b110101110010111101100001101 !
1#
#9
b110110101111100110100001101 *
b111100111110001100000001 (
b10000110110101111100101100000111 /
0#
b10000000000100000000110011 %
b100 .
#10
b101001100010110011001001010011 !
1#
#11
b11110100011011100110100111101 *
b111011001000111111000101110110 (
b10011110100011011100101111101101 /
0#
b10000000000101000000110011 %
b101 .
#12
b0 !
1#
#13
b1000110001011011111011110001100 *
b1110110110101000101011111101101 (
b11000110001011011111010011000011 /
0#
b10000000000110000000110011 %
b110 .
#14
b1 !
1#
#15
b11100011001101110010010011000110 *
b1111100111111011110100111111001 (
b1100011001101110010001100001001 /
0#
b10000000000111000000110011 %
b111 .
#16
b110000101001100110000001100001 !
1#
#17
b11010101000100111101001010101010 *
b11100010111101111000010011000101 (
b1010101000100111101000000111111 /
0#
b10000000000100000000110011 %
b1000 .
#18
b1111100111111011110100111111001 !
1#
#19
b10111011110100100111001001110111 *
b1110010101011111111011111100101 (
b111011110100100111000111100101 /
0#
b10000000000101000000110011 %
b1001 .
#20
b0 !
1#
#21
b1000111111011001101101110001111 *
b10001001001100101101011000010010 (
b11000111111011001101100101111011 /
0#
b10000000000110000000110011 %
b1010 .
#22
1#
#23
b11100111011101101001011011001110 *
b1111001001100000110100111110010 (
b1100111011101101001010010000001 /
0#
b10000000000111000000110011 %
b1011 .
#24
b11010001000111111011000110100001 !
1#
#25
b11100010110010100100111011000101 *
b11110100000000000111101011101000 (
b1100010110010100100110001110111 /
0#
b10000000000100000000110011 %
b1100 .
#26
b1111001001100000110100111110010 !
1#
#27
b11011110100011100010100010111101 *
b101110010110000100100101011100 (
b1011110100011100010011011011101 /
0#
b10000000000101000000110011 %
b1101 .
#28
b0 !
1#
#29
b10110010101001110010011001100101 *
b10010110101010110101100000101101 (
b110010101001110010010100110011 /
0#
b10000000000110000000110011 %
b1110 .
#30
1#
#31
b101011100111000011100001010 *
b10110001111011110110001001100011 (
b10000101011100111000010011111001 /
0#
b10000000000111000000110011 %
b1111 .
#32
b11100100000001000011000111001000 !
1#
#33
b10000011001000010000100100000 *
b11000000001110110010001010000000 (
b10010000011001000001111110101111 /
0#
b10000000000100000000110011 %
b10000 .
#34
b11011111101000000100100011 !
1#
#35
b11001110110011001100110010011101 *
b1010101011110000100010110101010 (
b1001110110011001100101011010101 /
0#
b10000000000101000000110011 %
b10001 .
#36
b11111111111111111111111111111101 !
1#
#37
b10001001100000111011100000010011 *
b11001011001000000011111010010110 (
b1001100000111011011111101011 /
0#
b10000000000110000000110011 %
b10010 .
#38
b0 !
1#
#39
b10101001101001111101011001010011 *
b10000110101111000011100000001101 (
b101001101001111101010001110001 /
0#
b10000000000111000000110011 %
b10011 .
#40
b11001011001000000011111010010110 !
1#
#41
b11101010101001100010101011010101 *
b110101100111111101110101101011 (
b1101010101001100010100111100111 /
0#
b10000000000100000000110011 %
b10100 .
#42
b10000110101111000011100000001101 !
1#
#43
b11010111010101100011111010101110 *
b10000001000101110100101000000010 (
b1010111010101100011110111001101 /
0#
b10000000000101000000110011 %
b10101 .
#44
b11111111111111111111111111111110 !
1#
#45
b11100111110001010111001011001111 *
b1110111111111110100100011101 (
b1100111110001010111000110100011 /
0#
b10000000000110000000110011 %
b10110 .
#46
b0 !
1#
#47
b101000010010110010100001010 *
b10001100001000100100100100011 (
b10000101000010010110001011101001 /
0#
b10000000000111000000110011 %
b10111 .
#48
b1110111111111110100100011101 !
1#
#49
b10011110001100010100110000111100 *
b11100101011100110000101011001010 (
b11110001100010100101100011111 /
0#
b10000000000100000000110011 %
b11000 .
#50
b10011010000001101000000101 !
1#
#51
b1000101001011100110000110001010 *
b1111001011010001011110111110010 (
b11000101001011100101111111000101 /
0#
b10000000000101000000110011 %
b11001 .
#52
b0 !
1#
#53
b11101100010010110011010011011000 *
b100000110001001011001101000001 (
b1101100010010110011001001011011 /
0#
b10000000000110000000110011 %
b11010 .
#54
b1 !
1#
#55
b11000100100010100001001010001001 *
b111100001000001111001101111000 (
b1000100100010100001000001100001 /
0#
b10000000000111000000110011 %
b11011 .
#56
b1101000011111110100000011001 !
1#
#57
b1011011000000100110010110110110 *
b1110101110001010000110111101011 (
b11011011000000100110001101010111 /
0#
b10000000000100000000110011 %
b11100 .
#58
b111100001000001111001101111000 !
1#
#59
b1010111000101010001001110101110 *
b1100011010010111111100111000110 (
b11010111000101010001000010111101 /
0#
b10000000000101000000110011 %
b11101 .
#60
b1 !
1#
#61
b10101000011111101110100101010 *
b11011110011101010000001010111100 (
b10010101000011111101101000010011 /
0#
b10000000000110000000110011 %
b11110 .
#62
1#
#63
b10111000100101111011111001110001 *
b10000101110101111001101000001011 (
b111000100101111011110011011001 /
0#
b10000000000111000000110011 %
b11111 .
#64
b11110011100001001101111111100110 !
1#
#65
b100111111100100101010101001111 *
b1000010111100100100000110000101 (
b10100111111100100101001010001111 /
0#
b10000000000100000000110011 %
b100000 .
#66
b10000101110101111001101000001011 !
1#
#67
b11101000001100011001100111010 *
b10011101110011000110000000111011 (
b10011101000001100011000010110101 /
0#
b10000000000101000000110011 %
b100001 .
#68
b1 !
1#
#69
b1010101010100100101100010101 *
b10111111001000110011001001111110 (
b10001010101010100100100011001011 /
0#
b10000000000110000000110011 %
b100010 .
#70
b101 !
1#
#71
b1101100100111000100101111011001 *
b1111000110110011001101111110001 (
b11101100100111000100100001010001 /
0#
b10000000000111000000110011 %
b100011 .
#72
b11111111001000001111010011111100 !
1#
#73
b100110001101011111101101001100 *
b110001001000110000011101100010 (
b10100110001101011111100011000111 /
0#
b10000000000100000000110011 %
b100100 .
#74
b1100001111010101000000011000 !
1#
#75
b1000111101110011010000110001111 *
b1001111101000010101010110011111 (
b11000111101110011001111110101101 /
0#
b10000000000101000000110011 %
b100101 .
#76
b1 !
1#
#77
b11011011110011010110000010110111 *
b1111100011011011010100111111000 (
b1011011110011010101111010000011 /
0#
b10000000000110000000110011 %
b100110 .
#78
1#
#79
b10101110011111011001010001011100 *
b11001111110001000101011010011111 (
b101110011111011001001011001001 /
0#
b10000000000111000000110011 %
b100111 .
#80
b1111110101011100110000011101 !
1#
#81
b1000100110111100011011110001001 *
b10101101110010111100000001011011 (
b11000100110111100011010111111111 /
0#
b10000000000100000000110011 %
b101000 .
#82
b100001010001101100001001000011 !
1#
#83
b11101000001000110011111011010000 *
b10100100101011100011001001001001 (
b1101000001000110011110110100101 /
0#
b10000000000101000000110011 %
b101001 .
#84
b11111111111111111111111111111111 !
1#
#85
b10101000110001111111110001010001 *
b11101011111111101100000011010111 (
b101000110001111111101100111011 /
0#
b10000000000110000000110011 %
b101010 .
#86
b0 !
1#
#87
b110000111010111111100001100 *
b1001011001000010010111110010110 (
b10000110000111010111110001000001 /
0#
b10000000000111000000110011 %
b101011 .
#88
b11101011111111101100000011010111 !
1#
#89
b1100100010101111110110111001000 *
b11100001001011001100111011000010 (
b11100100010101111110101000110111 /
0#
b10000000000100000000110011 %
b101100 .
#90
b1101111110011101100000110 !
1#
#91
b11110111100101110110100111101 *
b10111011100000100101101001110111 (
b10011110111100101110101010011101 /
0#
b10000000000101000000110011 %
b101101 .
#92
b0 !
1#
#93
b10111111000001010000000001111110 *
b1001000011001101101100010010 (
b111111000001001111111011110011 /
0#
b10000000000110000000110011 %
b101110 .
#94
b110 !
1#
#95
b11100110110011110011100111001 *
b110110111001011000000101101101 (
b10011100110110011110010010111001 /
0#
b10000000000111000000110011 %
b101111 .
#96
b1001000011001101101100010010 !
1#
#97
b11101001111010111111011011010011 *
b1111110100101000111100011111 (
b1101001111010111111010101101111 /
0#
b10000000000100000000110011 %
b110000 .
#98
b11010000010111001101000110100 !
1#
#99
b10111100000101001000100001111000 *
b1000010110110010010111110000101 (
b111100000101001000011010010101 /
0#
b10000000000101000000110011 %
b110001 .
#100
b0 !
1#
#101
b100100100010110100101101001001 *
b101101110110100101100101011011 (
b10100100100010110100100110101011 /
0#
b10000000000110000000110011 %
b110010 .
#102
1#
#103
b10101000011001010111100101010 *
b10011111111100101010111000111111 (
b10010101000011001010110000110001 /
0#
b10000000000111000000110011 %
b110011 .
#104
b1001010011110000111000010010 !
1#
#105
b11000011001111110011100010000110 *
b101100000101010110001101011000 (
b1000011001111110011011110100111 /
0#
b10000000000100000000110011 %
b110100 .
#106
b1100100110011110010000011001 !
1#
#107
b11001110001011111111001010011100 *
b11000111000110100000110010001110 (
b1001110001011111111000110001101 /
0#
b10000000000101000000110011 %
b110101 .
#108
b0 !
1#
#109
b10010011011111011011110000100110 *
b1111101001101011001100111111010 (
b10011011111011011101101100011 /
0#
b10000000000110000000110011 %
b110110 .
#110
1#
#111
b11010001100010111011010010100011 *
b111001100101100001011101110011 (
b1010001100010111011001010101001 /
0#
b10000000000111000000110011 %
b110111 .
#112
b10000101100110101011000100000 !
1#
#113
b11011001110100101001001010110011 *
b10010111100110011010100000101111 (
b1011001110100101001000011011111 /
0#
b10000000000100000000110011 %
b111000 .
#114
b111001100101100001011101110011 !
1#
#115
b100010001010010000110101000100 *
b10101111110110000101011001011111 (
b10100010001010010000101110000101 /
0#
b10000000000101000000110011 %
b111001 .
#116
b10 !
1#
#117
b11100101100110110011011011001011 *
b1111011111110001111110111110111 (
b1100101100110110011010000011011 /
0#
b10000000000110000000110011 %
b111010 .
#118
b101 !
1#
#119
b101101001010001101101101011010 *
b11110011000010010001101011100110 (
b10101101001010001101100000100001 /
0#
b10000000000111000000110011 %
b111011 .
#120
b10010011001011101100100100011 !
1#
#121
b11110110100000101110001011101101 *
b10100110011111100000100101001 (
b1110110100000101110000100010111 /
0#
b10000000000100000000110011 %
b111100 .
#122
b10001001111001101001000100100 !
1#
#123
b10110010100111111011011001100101 *
b11101101010100110110110011011010 (
b110010100111111011010001111101 /
0#
b10000000000101000000110011 %
b111101 .
#124
b11111111111111111111111111111110 !
1#
#125
b11101111101111101001010011011111 *
b11011010100010101110001010110101 (
b1101111101111101001001111010011 /
0#
b10000000000110000000110011 %
b111110 .
#126
b1 !
1#
#127
b100010001100011111111101000100 *
b111100111100010001100101111001 (
b10100010001100011111110010011001 /
0#
b10000000000111000000110011 %
b111111 .
#128
b11111011000011011011100011110111 !
1#
#129
b10101000010010000101100101010 *
b11101000011101000000110011010000 (
b10010101000010010000100001001111 /
0#
b10000000000100000000110011 %
b1000000 .
#130
b11010101111110001101000110101 !
1#
#131
b111011011111100111100001110 *
b1010101111101101010110110101011 (
b10000111011011111100110001110101 /
0#
b10000000000101000000110011 %
b1000001 .
#132
b11111111111111111111111111111111 !
1#
#133
b11001101010111101011110010011010 *
b1101110010111011010110111011100 (
b1001101010111101011101010001011 /
0#
b10000000000110000000110011 %
b1000010 .
#134
b1011 !
1#
#135
b11100001111100010000001011000011 *
b11111110110111110111001011111101 (
b1100001111100010000000000010001 /
0#
b10000000000111000000110011 %
b1000011 .
#136
b1001000110110010011100010000 !
1#
#137
b100111011110011110100101001110 *
b101011000011101110110101010110 (
b10100111011110011110011010000111 /
0#
b10000000000100000000110011 %
b1000100 .
#138
b11100111011100111000000111010 !
1#
#139
b10000101001100010011010000001010 *
b10110011110110010111011001100111 (
b101001100010011001101101101 /
0#
b10000000000101000000110011 %
b1000101 .
#140
b1 !
1#
#141
b10011100000011101000101000111000 *
b1011011011011111011100110110110 (
b11100000011101000100001000011 /
0#
b10000000000110000000110011 %
b1000110 .
#142
1#
#143
b11011100001010111100010010111000 *
b111100110100011000011101111001 (
b1011100001010111100001010001001 /
0#
b10000000000111000000110011 %
b1000111 .
#144
b1011011011011111011100110110110 !
1#
#145
b1001001110001100101110110010011 *
b1001010011101001011111110010100 (
b11001001110001100101101110111111 /
0#
b10000000000100000000110011 %
b1001000 .
#146
b111100110100011000011101111001 !
1#
#147
b10101100101101111100101001011001 *
b10000010001111110010110000000100 (
b101100101101111100100101100101 /
0#
b10000000000101000000110011 %
b1001001 .
#148
b1 !
1#
#149
b10100110111111001101111001001101 *
b1101101110010110110100111011011 (
b100110111111001101110011111011 /
0#
b10000000000110000000110011 %
b1001010 .
#150
b0 !
1#
#151
b10110110101001000010011001101101 *
b1101100101100001011011111011001 (
b110110101001000010010000000001 /
0#
b10000000000111000000110011 %
b1001011 .
#152
b10100110010000100100000101000 !
1#
#153
b1100101001110110100100111001010 *
b10111011010001011110001001110110 (
b11100101001110110100011111110111 /
0#
b10000000000100000000110011 %
b1001100 .
#154
b1101100101100001011011111011001 !
1#
#155
b1001010100100110111000110010101 *
b1011011000101110010110110110110 (
b11001010100100110110111001011101 /
0#
b10000000000101000000110011 %
b1001101 .
#156
b0 !
1#
#157
b10011101001001101100000100 *
b10100011000001110001101001000110 (
b10000010011101001001100010110011 /
0#
b10000000000110000000110011 %
b1001110 .
#158
b1 !
1#
#159
b110100100110000000011101101001 *
b1111011110100100110000111110111 (
b10110100100110000000010001111001 /
0#
b10000000000111000000110011 %
b1001111 .
#160
b11111101111000011000000111011010 !
1#
#161
b1000100000000011000110110001000 *
b11011010011011101011101010110100 (
b11000100000000011000101100101111 /
0#
b10000000000100000000110011 %
b1010000 .
#162
b10010101000100101001100100101 !
1#
#163
b10010110100100000000010000101101 *
b10100011111001101100100101000 (
b10110100100000000001001010101 /
0#
b10000000000101000000110011 %
b1010001 .
#164
b0 !
1#
#165
b10010111010111001001110000101110 *
b11100011110001010011000011000111 (
b10111010111001001101101101011 /
0#
b10000000000110000000110011 %
b1010010 .
#166
1#
#167
b1110010000010100010100011100 *
b10000100011101111110010000001000 (
b10001110010000010100001111110001 /
0#
b10000000000111000000110011 %
b1010011 .
#168
b11100011110001010011000011000111 !
1#
#169
b10100100111100000011100101001 *
b11111110101001111010011011111101 (
b10010100100111100000010101100111 /
0#
b10000000000100000000110011 %
b1010100 .
#170
b100001011000111011000001100 !
1#
#171
b1000011001101010110011110000110 *
b10001110001101111001000000011100 (
b11000011001101010110010101001101 /
0#
b10000000000101000000110011 %
b1010101 .
#172
b0 !
1#
#173
b10011110101101111100011000111101 *
b11101101001101000000100011011010 (
b11110101101111100010100100011 /
0#
b10000000000110000000110011 %
b1010110 .
#174
b10 !
1#
#175
b10111000010101011100010001110000 *
b110011010011101010011101100110 (
b111000010101011100001001101001 /
0#
b10000000000111000000110011 %
b1010111 .
#176
b11101101001101000000100011011010 !
1#
#177
b1011101011100011001100110111010 *
b10111001111101010000010001110011 (
b11011101011100011001011010011111 /
0#
b10000000000100000000110011 %
b1011000 .
#178
b110011010011101010011101100110 !
1#
#179
b1111101010001110111100111111010 *
b101111001110101011001101011110 (
b11111101010001110111011101000101 /
0#
b10000000000101000000110011 %
b1011001 .
#180
b0 !
1#
#181
b10001101001001001111011000011010 *
b1101010100011100000010111010101 (
b1101001001001111010111011011 /
0#
b10000000000110000000110011 %
b1011010 .
#182
1#
#183
b11011100001110110000100110111 *
b11011100111100000000000010111001 (
b10011011100001110101111111100001 /
0#
b10000000000111000000110011 %
b1011011 .
#184
b1101010100011100000010111010101 !
1#
#185
b1100000001110010010000111000000 *
b1001011001001110011011110010110 (
b11100000001110010001111011010111 /
0#
b10000000000100000000110011 %
b1011100 .
#186
b101101001111011100000001 !
1#
#187
b11011011010001100001101010110110 *
b10011001001011001111100100110 (
b1011011010001100001100000111101 /
0#
b10000000000101000000110011 %
b1011101 .
#188
b0 !
1#
#189
b1101110010111110000111111011100 *
b111110100110011000001101111101 (
b11101110010111110000110110010011 /
0#
b10000000000110000000110011 %
b1011110 .
#190
1#
#191
b111100000000111111111101111000 *
b1000011011000010101011110000110 (
b10111100000000111111110001011001 /
0#
b10000000000111000000110011 %
b1011111 .
#192
b111110100110011000001101111101 !
1#
#193
b11101101100011011000000011011011 *
b111111010110101001101101111110 (
b1101101100011010111111000001111 /
0#
b10000000000100000000110011 %
b1100000 .
#194
b111010111010101100000001110 !
1#
#195
b111100111011010010101101111001 *
b11100111110000111011011011001111 (
b10111100111011010010100000110101 /
0#
b10000000000101000000110011 %
b1100001 .
#196
b11111111111111111111111111111101 !
1#
#197
b10110000101111001110111001100001 *
b11111101001010001110010011111010 (
b110000101111001110110001001011 /
0#
b10000000000110000000110011 %
b1100010 .
#198
b11 !
1#
#199
b11010000111101010111100010100001 *
b1011100101000000100100010111 (
b1010000111101010111011111010001 /
0#
b10000000000111000000110011 %
b1100011 .
#200
b11111101001010001110010011111010 !
1#
#201
b10101000011000111001011001010000 *
b1000011011101111001000110000110 (
b101000011000111001010001000111 /
0#
b10000000000100000000110011 %
b1100100 .
#202
b1011100101000000100100010111 !
1#
#203
b10011010101101001000100000110101 *
b1111010100011000101100111110101 (
b11010101101001000011100101101 /
0#
b10000000000101000000110011 %
b1100101 .
#204
b0 !
1#
#205
b1100000101100010111010111000001 *
b10010100100110101000101000101001 (
b11100000101100010111001000000011 /
0#
b10000000000110000000110011 %
b1100110 .
#206
1#
#207
b11001100000000011011010010011000 *
b11100010111001010111010011000101 (
b1001100000000011011001001001001 /
0#
b10000000000111000000110011 %
b1100111 .
#208
b11110101010010111111111111101010 !
1#
#209
b10111001100011000100001001110011 *
b100101101100100111101101001011 (
b111001100011000100000101111111 /
0#
b10000000000100000000110011 %
b1101000 .
#210
b10110111000111100000000101101 !
1#
#211
b11000101010100000001011010001010 *
b11110110001000101110011011101100 (
b1000101010100000001010100100101 /
0#
b10000000000101000000110011 %
b1101001 .
#212
b0 !
1#
#213
b11010100010010111000000010101000 *
b100111010110001101000101001110 (
b1010100010010110111111010111011 /
0#
b10000000000110000000110011 %
b1101010 .
#214
b1 !
1#
#215
b11010000110010101000110010100001 *
b1010100100111101111110110101001 (
b1010000110010101000101111000001 /
0#
b10000000000111000000110011 %
b1101011 .
#216
b100111010110001101000101001110 !
1#
#217
b11110011001101000110011011100110 *
b111000010111011100100001110 (
b1110011001101000110010110110111 /
0#
b10000000000100000000110011 %
b1101100 .
#218
b1010100100111101111110110101001 !
1#
#219
b10101001011111011010100101010 *
b11001111110101101100000010011111 (
b10010101001011111011001000011101 /
0#
b10000000000101000000110011 %
b1101101 .
#220
b0 !
1#
#221
b11000110101101011111010010001101 *
b10101010110100001110100101010 (
b1000110101101011111001001110011 /
0#
b10000000000110000000110011 %
b1101110 .
#222
b1001 !
1#
#223
b10011100011011011110011000111000 *
b1001111011101011111111110011110 (
b11100011011011110010000111001 /
0#
b10000000000111000000110011 %
b1101111 .
#224
b10101010110100001110100101010 !
1#
#225
b1100100011001001110001111001000 *
b10111100110011111010100001111001 (
b11100100011001001110000011101111 /
0#
b10000000000100000000110011 %
b1110000 .
#226
b1001111011101011111111110011110 !
1#
#227
b1001111111110100000100010011 *
b1100101001000110100010111001010 (
b10001001111111110011111000010101 /
0#
b10000000000101000000110011 %
b1110001 .
#228
b0 !
1#
#229
b11100011101101111010111011000111 *
b110101101000001100100101101011 (
b1100011101101111010110100101011 /
0#
b10000000000110000000110011 %
b1110010 .
#230
b1010 !
1#
#231
b1011101000001011001110110111010 *
b1011011000010111101110110110110 (
b11011101000001011001101110110001 /
0#
b10000000000111000000110011 %
b1110011 .
#232
b11001010110000111100000110010 !
1#
#233
b1011100100000101001010110111001 *
b1100010000101101010101111000100 (
b11011100100000101001001100100111 /
0#
b10000000000100000000110011 %
b1110100 .
#234
b1011011000010111101110110110110 !
1#
#235
b11011010001001101001101010110100 *
b1001001001011111101001110010010 (
b1011010001001101001100100001101 /
0#
b10000000000101000000110011 %
b1110101 .
#236
b1 !
1#
#237
b11000011001100111001000010000110 *
b111111101110110011101101111111 (
b1000011001100111000111011100011 /
0#
b10000000000110000000110011 %
b1110110 .
#238
b0 !
1#
#239
b11111001001001111001010011110010 *
b1111101011011011111010111111010 (
b1111001001001111001001000101001 /
0#
b10000000000111000000110011 %
b1110111 .
#240
b10111011101100110000000101 !
1#
#241
b11011110110011100101111010111101 *
b11001010001010010000100110010 (
b1011110110011100101110001011111 /
0#
b10000000000100000000110011 %
b1111000 .
#242
b1111101011011011111010111111010 !
1#
#243
b11110010010010011010010011100100 *
b1000010010011111100110110000100 (
b1110010010010011010001100000101 /
0#
b10000000000101000000110011 %
b1111001 .
#244
b0 !
1#
#245
b1010100101010000111100110101001 *
b1100101010000111100111111001010 (
b11010100101010000111011110011011 /
0#
b10000000000110000000110011 %
b1111010 .
#246
1#
#247
b1000111011001011010100110001110 *
b11010000100101011010100010100001 (
b11000111011001011010011110100001 /
0#
b10000000000111000000110011 %
b1111011 .
#248
b10000100110110101011000100001 !
1#
#249
b10000101111001010001111000001011 *
b11111101100010110110101011111011 (
b101111001010001110010010111 /
0#
b10000000000100000000110011 %
b1111100 .
#250
b1000001110010100101010110000101 !
1#
#251
b1100100110010000011110111001001 *
b11110111100000101001000011101111 (
b11100100110010000011101111111101 /
0#
b10000000000101000000110011 %
b1111101 .
#252
b0 !
1#
#253
b10111010101100010100100001110101 *
b11011011000001110010100110110 (
b111010101100010100011101010011 /
0#
b10000000000110000000110011 %
b1111110 .
#254
b10 !
1#
#255
b110101110011011011111101101011 *
b11000111111010000101011010001111 (
b10110101110011011011110000011001 /
0#
b10000000000111000000110011 %
b1111111 .
#256
b11011011000001110010100110110 !
1#
#257
b11010111001111111011010010101110 *
b1000100011001011110011110001000 (
b1010111001111111011001111001111 /
0#
b10000000000100000000110011 %
b10000000 .
#258
b100110011111110001100001001110 !
1#
#259
b1001001001111100100010110010010 *
b1001101111100111000000110011011 (
b11001001001111100100001111110101 /
0#
b10000000000101000000110011 %
b10000001 .
#260
b11111111111111111111111111111111 !
1#
#261
b10010110100001001110000000101101 *
b10100010001001101111100101000 (
b10110100001001101111000001011 /
0#
b10000000000110000000110011 %
b10000010 .
#262
b1 !
1#
