core/riscv/riscv_divider.v
//-----------------------------------------------------------------
//                         RISC-V Core
//                            V1.0.1
//                     Ultra-Embedded.com
//                     Copyright 2014-2019
//
//                   admin@ultra-embedded.com
//
//                       License: BSD
//-----------------------------------------------------------------
//
// Copyright (c) 2014-2019, Ultra-Embedded.com
// All rights reserved.
// 
// Redistribution and use in source and binary forms, with or without
// modification, are permitted provided that the following conditions 
// are met:
//   - Redistributions of source code must retain the above copyright
//     notice, this list of conditions and the following disclaimer.
//   - Redistributions in binary form must reproduce the above copyright
//     notice, this list of conditions and the following disclaimer 
//     in the documentation and/or other materials provided with the 
//     distribution.
//   - Neither the name of the author nor the names of its contributors 
//     may be used to endorse or promote products derived from this 
//     software without specific prior written permission.
// 
// THIS SOFTWARE IS PROVIDED BY THE COPYRIGHT HOLDERS AND CONTRIBUTORS 
// "AS IS" AND ANY EXPRESS OR IMPLIED WARRANTIES, INCLUDING, BUT NOT 
// LIMITED TO, THE IMPLIED WARRANTIES OF MERCHANTABILITY AND FITNESS FOR 
// A PARTICULAR PURPOSE ARE DISCLAIMED. IN NO EVENT SHALL THE AUTHOR BE 
// LIABLE FOR ANY DIRECT, INDIRECT, INCIDENTAL, SPECIAL, EXEMPLARY, OR 
// CONSEQUENTIAL DAMAGES (INCLUDING, BUT NOT LIMITED TO, PROCUREMENT OF 
// SUBSTITUTE GOODS OR SERVICES; LOSS OF USE, DATA, OR PROFITS; OR 
// BUSINESS INTERRUPTION) HOWEVER CAUSED AND ON ANY THEORY OF 
// LIABILITY, WHETHER IN CONTRACT, STRICT LIABILITY, OR TORT
// (INCLUDING NEGLIGENCE OR OTHERWISE) ARISING IN ANY WAY OUT OF 
// THE USE OF THIS SOFTWARE, EVEN IF ADVISED OF THE POSSIBILITY OF 
// SUCH DAMAGE.
//-----------------------------------------------------------------

module riscv_divider
(
    // Inputs
     input           clk_i
    ,input           rst_i
    ,input           opcode_valid_i
    ,input  [ 31:0]  opcode_opcode_i
    ,input  [ 31:0]  opcode_pc_i
    ,input           opcode_invalid_i
    ,input  [  4:0]  opcode_rd_idx_i
    ,input  [  4:0]  opcode_ra_idx_i
    ,input  [  4:0]  opcode_rb_idx_i
    ,input  [ 31:0]  opcode_ra_operand_i
    ,input  [ 31:0]  opcode_rb_operand_i

    // Outputs
    ,output          writeback_valid_o
    ,output [ 31:0]  writeback_value_o
);



//-----------------------------------------------------------------
// Includes
//-----------------------------------------------------------------
`include "riscv_defs.v"

// Stage 1

reg [31:0] opcode_ra_operand_q_s1;
reg [31:0] opcode_rb_operand_q_s1;
reg valid_q_s1;
reg [31:0] opcode_opcode_q_s1;

always @ (posedge clk_i or posedge rst_i) begin
    if (rst_i) begin
        opcode_ra_operand_q_s1 <= 0;
        opcode_rb_operand_q_s1 <= 0;
        valid_q_s1 <= 0;
        opcode_opcode_q_s1 <= 0;
    end else begin
        valid_q_s1 <= opcode_valid_i;
        opcode_ra_operand_q_s1 <= opcode_ra_operand_i;
        opcode_rb_operand_q_s1 <= opcode_rb_operand_i;
        opcode_opcode_q_s1 <= opcode_opcode_i;
    end
end

// Stage 2

reg          valid_q;
reg  [31:0]  wb_result_q;

wire div_rem_inst_w     = ((opcode_opcode_q_s1 & `INST_DIV_MASK) == `INST_DIV)  || 
                          ((opcode_opcode_q_s1 & `INST_DIVU_MASK) == `INST_DIVU) ||
                          ((opcode_opcode_q_s1 & `INST_REM_MASK) == `INST_REM)  ||
                          ((opcode_opcode_q_s1 & `INST_REMU_MASK) == `INST_REMU);

wire signed_operation_w = ((opcode_opcode_q_s1 & `INST_DIV_MASK) == `INST_DIV) || ((opcode_opcode_q_s1 & `INST_REM_MASK) == `INST_REM);
wire div_operation_w    = ((opcode_opcode_q_s1 & `INST_DIV_MASK) == `INST_DIV) || ((opcode_opcode_q_s1 & `INST_DIVU_MASK) == `INST_DIVU);

always @ (posedge clk_i or posedge rst_i) begin
    if (rst_i) begin
        valid_q <= 0;
        wb_result_q <= 0;
    end else if (div_rem_inst_w) begin
        valid_q <= valid_q_s1 && div_rem_inst_w;
        if (div_operation_w) begin
            if (signed_operation_w) begin
                wb_result_q <= $signed(opcode_ra_operand_q_s1) / $signed(opcode_rb_operand_q_s1);
            end else begin
                wb_result_q <= $unsigned(opcode_ra_operand_q_s1) / $unsigned(opcode_rb_operand_q_s1);
            end
        end else begin
            if (signed_operation_w) begin
                wb_result_q <= $signed(opcode_ra_operand_q_s1) % $signed(opcode_rb_operand_q_s1);
            end else begin
                wb_result_q <= $unsigned(opcode_ra_operand_q_s1) % $unsigned(opcode_rb_operand_q_s1);
            end
        end
    end
end

assign writeback_valid_o = valid_q;
assign writeback_value_o = wb_result_q;



endmodule

testbench/divider/divider_tb.v
`include "../../core/riscv/riscv_defs.v"
`include "../../core/riscv/riscv_divider.v"

module tb;
	reg           clk_i;
	reg           rst_i;
	reg           opcode_valid_i;
	reg  [ 31:0]  opcode_opcode_i;
	reg  [ 31:0]  opcode_pc_i;
	reg           opcode_invalid_i;
	reg  [  4:0]  opcode_rd_idx_i;
	reg  [  4:0]  opcode_ra_idx_i;
	reg  [  4:0]  opcode_rb_idx_i;
	reg  [ 31:0]  opcode_ra_operand_i;
	reg  [ 31:0]  opcode_rb_operand_i;
	wire          writeback_valid_o;
	wire [ 31:0]  writeback_value_o;

	riscv_divider dut (
		.clk_i(clk_i),
		.rst_i(rst_i),
		.opcode_valid_i(opcode_valid_i),
		.opcode_opcode_i(opcode_opcode_i),
		.opcode_pc_i(opcode_pc_i),
		.opcode_invalid_i(opcode_invalid_i),
		.opcode_rd_idx_i(opcode_rd_idx_i),
		.opcode_ra_idx_i(opcode_ra_idx_i),
		.opcode_rb_idx_i(opcode_rb_idx_i),
		.opcode_ra_operand_i(opcode_ra_operand_i),
		.opcode_rb_operand_i(opcode_rb_operand_i),
		.writeback_valid_o(writeback_valid_o),
		.writeback_value_o(writeback_value_o)
	);

	integer seed;
	integer i;

	initial begin
		$dumpfile(".divider_tb.vcd");
		$dumpvars(1, tb);

		clk_i = 0;
		rst_i = 1;
		opcode_valid_i = 0;
		opcode_opcode_i = 0;
		opcode_pc_i = 0;
		opcode_invalid_i = 0;
		opcode_rd_idx_i = 0;
		opcode_ra_idx_i = 0;
		opcode_rb_idx_i = 0;
		opcode_ra_operand_i = 0;
		opcode_rb_operand_i = 0;
		#1;
		for (i = 0; i < 1000; i += 1) begin
			clk_i = !clk_i;
			#1;
		end
	end

endmodule

testbench/divider/.divider_tb.vcd
$date
	Fri Oct 17 15:19:48 2025
$end
$version
	Icarus Verilog
$end
$timescale
	1s
$end
$scope module tb $end
$var wire 32 ! writeback_value_o [31:0] $end
$var wire 1 " writeback_valid_o $end
$var reg 1 # clk_i $end
$var reg 1 $ opcode_invalid_i $end
$var reg 32 % opcode_opcode_i [31:0] $end
$var reg 32 & opcode_pc_i [31:0] $end
$var reg 5 ' opcode_ra_idx_i [4:0] $end
$var reg 32 ( opcode_ra_operand_i [31:0] $end
$var reg 5 ) opcode_rb_idx_i [4:0] $end
$var reg 32 * opcode_rb_operand_i [31:0] $end
$var reg 5 + opcode_rd_idx_i [4:0] $end
$var reg 1 , opcode_valid_i $end
$var reg 1 - rst_i $end
$var integer 32 . i [31:0] $end
$upscope $end
$enddefinitions $end
$comment Show the parameter values. $end
$dumpall
$end
#0
$dumpvars
bx .
1-
0,
b0 +
b0 *
b0 )
b0 (
b0 '
b0 &
b0 %
0$
0#
0"
b0 !
$end
#1
1#
b0 .
#2
0#
b1 .
#3
1#
b10 .
#4
0#
b11 .
#5
1#
b100 .
#6
0#
b101 .
#7
1#
b110 .
#8
0#
b111 .
#9
1#
b1000 .
#10
0#
b1001 .
#11
1#
b1010 .
#12
0#
b1011 .
#13
1#
b1100 .
#14
0#
b1101 .
#15
1#
b1110 .
#16
0#
b1111 .
#17
1#
b10000 .
#18
0#
b10001 .
#19
1#
b10010 .
#20
0#
b10011 .
#21
1#
b10100 .
#22
0#
b10101 .
#23
1#
b10110 .
#24
0#
b10111 .
#25
1#
b11000 .
#26
0#
b11001 .
#27
1#
b11010 .
#28
0#
b11011 .
#29
1#
b11100 .
#30
0#
b11101 .
#31
1#
b11110 .
#32
0#
b11111 .
#33
1#
b100000 .
#34
0#
b100001 .
#35
1#
b100010 .
#36
0#
b100011 .
#37
1#
b100100 .
#38
0#
b100101 .
#39
1#
b100110 .
#40
0#
b100111 .
#41
1#
b101000 .
#42
0#
b101001 .
#43
1#
b101010 .
#44
0#
b101011 .
#45
1#
b101100 .
#46
0#
b101101 .
#47
1#
b101110 .
#48
0#
b101111 .
#49
1#
b110000 .
#50
0#
b110001 .
#51
1#
b110010 .
#52
0#
b110011 .
#53
1#
b110100 .
#54
0#
b110101 .
#55
1#
b110110 .
#56
0#
b110111 .
#57
1#
b111000 .
#58
0#
b111001 .
#59
1#
b111010 .
#60
0#
b111011 .
#61
1#
b111100 .
#62
0#
b111101 .
#63
1#
b111110 .
#64
0#
b111111 .
#65
1#
b1000000 .
#66
0#
b1000001 .
#67
1#
b1000010 .
#68
0#
b1000011 .
#69
1#
b1000100 .
#70
0#
b1000101 .
#71
1#
b1000110 .
#72
0#
b1000111 .
#73
1#
b1001000 .
#74
0#
b1001001 .
#75
1#
b1001010 .
#76
0#
b1001011 .
#77
1#
b1001100 .
#78
0#
b1001101 .
#79
1#
b1001110 .
#80
0#
b1001111 .
#81
1#
b1010000 .
#82
0#
b1010001 .
#83
1#
b1010010 .
#84
0#
b1010011 .
#85
1#
b1010100 .
#86
0#
b1010101 .
#87
1#
b1010110 .
#88
0#
b1010111 .
#89
1#
b1011000 .
#90
0#
b1011001 .
#91
1#
b1011010 .
#92
0#
b1011011 .
#93
1#
b1011100 .
#94
0#
b1011101 .
#95
1#
b1011110 .
#96
0#
b1011111 .
#97
1#
b1100000 .
#98
0#
b1100001 .
#99
1#
b1100010 .
#100
0#
b1100011 .
#101
1#
b1100100 .
#102
0#
b1100101 .
#103
1#
b1100110 .
#104
0#
b1100111 .
#105
1#
b1101000 .
#106
0#
b1101001 .
#107
1#
b1101010 .
#108
0#
b1101011 .
#109
1#
b1101100 .
#110
0#
b1101101 .
#111
1#
b1101110 .
#112
0#
b1101111 .
#113
1#
b1110000 .
#114
0#
b1110001 .
#115
1#
b1110010 .
#116
0#
b1110011 .
#117
1#
b1110100 .
#118
0#
b1110101 .
#119
1#
b1110110 .
#120
0#
b1110111 .
#121
1#
b1111000 .
#122
0#
b1111001 .
#123
1#
b1111010 .
#124
0#
b1111011 .
#125
1#
b1111100 .
#126
0#
b1111101 .
#127
1#
b1111110 .
#128
0#
b1111111 .
#129
1#
b10000000 .
#130
0#
b10000001 .
#131
1#
b10000010 .
#132
0#
b10000011 .
#133
1#
b10000100 .
#134
0#
b10000101 .
#135
1#
b10000110 .
#136
0#
b10000111 .
#137
1#
b10001000 .
#138
0#
b10001001 .
#139
1#
b10001010 .
#140
0#
b10001011 .
#141
1#
b10001100 .
#142
0#
b10001101 .
#143
1#
b10001110 .
#144
0#
b10001111 .
#145
1#
b10010000 .
#146
0#
b10010001 .
#147
1#
b10010010 .
#148
0#
b10010011 .
#149
1#
b10010100 .
#150
0#
b10010101 .
#151
1#
b10010110 .
#152
0#
b10010111 .
#153
1#
b10011000 .
#154
0#
b10011001 .
#155
1#
b10011010 .
#156
0#
b10011011 .
#157
1#
b10011100 .
#158
0#
b10011101 .
#159
1#
b10011110 .
#160
0#
b10011111 .
#161
1#
b10100000 .
#162
0#
b10100001 .
#163
1#
b10100010 .
#164
0#
b10100011 .
#165
1#
b10100100 .
#166
0#
b10100101 .
#167
1#
b10100110 .
#168
0#
b10100111 .
#169
1#
b10101000 .
#170
0#
b10101001 .
#171
1#
b10101010 .
#172
0#
b10101011 .
#173
1#
b10101100 .
#174
0#
b10101101 .
#175
1#
b10101110 .
#176
0#
b10101111 .
#177
1#
b10110000 .
#178
0#
b10110001 .
#179
1#
b10110010 .
#180
0#
b10110011 .
#181
1#
b10110100 .
#182
0#
b10110101 .
#183
1#
b10110110 .
#184
0#
b10110111 .
#185
1#
b10111000 .
#186
0#
b10111001 .
#187
1#
b10111010 .
#188
0#
b10111011 .
#189
1#
b10111100 .
#190
0#
b10111101 .
#191
1#
b10111110 .
#192
0#
b10111111 .
#193
1#
b11000000 .
#194
0#
b11000001 .
#195
1#
b11000010 .
#196
0#
b11000011 .
#197
1#
b11000100 .
#198
0#
b11000101 .
#199
1#
b11000110 .
#200
0#
b11000111 .
#201
1#
b11001000 .
#202
0#
b11001001 .
#203
1#
b11001010 .
#204
0#
b11001011 .
#205
1#
b11001100 .
#206
0#
b11001101 .
#207
1#
b11001110 .
#208
0#
b11001111 .
#209
1#
b11010000 .
#210
0#
b11010001 .
#211
1#
b11010010 .
#212
0#
b11010011 .
#213
1#
b11010100 .
#214
0#
b11010101 .
#215
1#
b11010110 .
#216
0#
b11010111 .
#217
1#
b11011000 .
#218
0#
b11011001 .
#219
1#
b11011010 .
#220
0#
b11011011 .
#221
1#
b11011100 .
#222
0#
b11011101 .
#223
1#
b11011110 .
#224
0#
b11011111 .
#225
1#
b11100000 .
#226
0#
b11100001 .
#227
1#
b11100010 .
#228
0#
b11100011 .
#229
1#
b11100100 .
#230
0#
b11100101 .
#231
1#
b11100110 .
#232
0#
b11100111 .
#233
1#
b11101000 .
#234
0#
b11101001 .
#235
1#
b11101010 .
#236
0#
b11101011 .
#237
1#
b11101100 .
#238
0#
b11101101 .
#239
1#
b11101110 .
#240
0#
b11101111 .
#241
1#
b11110000 .
#242
0#
b11110001 .
#243
1#
b11110010 .
#244
0#
b11110011 .
#245
1#
b11110100 .
#246
0#
b11110101 .
#247
1#
b11110110 .
#248
0#
b11110111 .
#249
1#
b11111000 .
#250
0#
b11111001 .
#251
1#
b11111010 .
#252
0#
b11111011 .
#253
1#
b11111100 .
#254
0#
b11111101 .
#255
1#
b11111110 .
#256
0#
b11111111 .
#257
1#
b100000000 .
#258
0#
b100000001 .
#259
1#
b100000010 .
#260
0#
b100000011 .
#261
1#
b100000100 .
#262
0#
b100000101 .
#263
1#
b100000110 .
#264
0#
b100000111 .
#265
1#
b100001000 .
#266
0#
b100001001 .
#267
1#
b100001010 .
#268
0#
b100001011 .
#269
1#
b100001100 .
#270
0#
b100001101 .
#271
1#
b100001110 .
#272
0#
b100001111 .
#273
1#
b100010000 .
#274
0#
b100010001 .
#275
1#
b100010010 .
#276
0#
b100010011 .
#277
1#
b100010100 .
#278
0#
b100010101 .
#279
1#
b100010110 .
#280
0#
b100010111 .
#281
1#
b100011000 .
#282
0#
b100011001 .
#283
1#
b100011010 .
#284
0#
b100011011 .
#285
1#
b100011100 .
#286
0#
b100011101 .
#287
1#
b100011110 .
#288
0#
b100011111 .
#289
1#
b100100000 .
#290
0#
b100100001 .
#291
1#
b100100010 .
#292
0#
b100100011 .
#293
1#
b100100100 .
#294
0#
b100100101 .
#295
1#
b100100110 .
#296
0#
b100100111 .
#297
1#
b100101000 .
#298
0#
b100101001 .
#299
1#
b100101010 .
#300
0#
b100101011 .
#301
1#
b100101100 .
#302
0#
b100101101 .
#303
1#
b100101110 .
#304
0#
b100101111 .
#305
1#
b100110000 .
#306
0#
b100110001 .
#307
1#
b100110010 .
#308
0#
b100110011 .
#309
1#
b100110100 .
#310
0#
b100110101 .
#311
1#
b100110110 .
#312
0#
b100110111 .
#313
1#
b100111000 .
#314
0#
b100111001 .
#315
1#
b100111010 .
#316
0#
b100111011 .
#317
1#
b100111100 .
#318
0#
b100111101 .
#319
1#
b100111110 .
#320
0#
b100111111 .
#321
1#
b101000000 .
#322
0#
b101000001 .
#323
1#
b101000010 .
#324
0#
b101000011 .
#325
1#
b101000100 .
#326
0#
b101000101 .
#327
1#
b101000110 .
#328
0#
b101000111 .
#329
1#
b101001000 .
#330
0#
b101001001 .
#331
1#
b101001010 .
#332
0#
b101001011 .
#333
1#
b101001100 .
#334
0#
b101001101 .
#335
1#
b101001110 .
#336
0#
b101001111 .
#337
1#
b101010000 .
#338
0#
b101010001 .
#339
1#
b101010010 .
#340
0#
b101010011 .
#341
1#
b101010100 .
#342
0#
b101010101 .
#343
1#
b101010110 .
#344
0#
b101010111 .
#345
1#
b101011000 .
#346
0#
b101011001 .
#347
1#
b101011010 .
#348
0#
b101011011 .
#349
1#
b101011100 .
#350
0#
b101011101 .
#351
1#
b101011110 .
#352
0#
b101011111 .
#353
1#
b101100000 .
#354
0#
b101100001 .
#355
1#
b101100010 .
#356
0#
b101100011 .
#357
1#
b101100100 .
#358
0#
b101100101 .
#359
1#
b101100110 .
#360
0#
b101100111 .
#361
1#
b101101000 .
#362
0#
b101101001 .
#363
1#
b101101010 .
#364
0#
b101101011 .
#365
1#
b101101100 .
#366
0#
b101101101 .
#367
1#
b101101110 .
#368
0#
b101101111 .
#369
1#
b101110000 .
#370
0#
b101110001 .
#371
1#
b101110010 .
#372
0#
b101110011 .
#373
1#
b101110100 .
#374
0#
b101110101 .
#375
1#
b101110110 .
#376
0#
b101110111 .
#377
1#
b101111000 .
#378
0#
b101111001 .
#379
1#
b101111010 .
#380
0#
b101111011 .
#381
1#
b101111100 .
#382
0#
b101111101 .
#383
1#
b101111110 .
#384
0#
b101111111 .
#385
1#
b110000000 .
#386
0#
b110000001 .
#387
1#
b110000010 .
#388
0#
b110000011 .
#389
1#
b110000100 .
#390
0#
b110000101 .
#391
1#
b110000110 .
#392
0#
b110000111 .
#393
1#
b110001000 .
#394
0#
b110001001 .
#395
1#
b110001010 .
#396
0#
b110001011 .
#397
1#
b110001100 .
#398
0#
b110001101 .
#399
1#
b110001110 .
#400
0#
b110001111 .
#401
1#
b110010000 .
#402
0#
b110010001 .
#403
1#
b110010010 .
#404
0#
b110010011 .
#405
1#
b110010100 .
#406
0#
b110010101 .
#407
1#
b110010110 .
#408
0#
b110010111 .
#409
1#
b110011000 .
#410
0#
b110011001 .
#411
1#
b110011010 .
#412
0#
b110011011 .
#413
1#
b110011100 .
#414
0#
b110011101 .
#415
1#
b110011110 .
#416
0#
b110011111 .
#417
1#
b110100000 .
#418
0#
b110100001 .
#419
1#
b110100010 .
#420
0#
b110100011 .
#421
1#
b110100100 .
#422
0#
b110100101 .
#423
1#
b110100110 .
#424
0#
b110100111 .
#425
1#
b110101000 .
#426
0#
b110101001 .
#427
1#
b110101010 .
#428
0#
b110101011 .
#429
1#
b110101100 .
#430
0#
b110101101 .
#431
1#
b110101110 .
#432
0#
b110101111 .
#433
1#
b110110000 .
#434
0#
b110110001 .
#435
1#
b110110010 .
#436
0#
b110110011 .
#437
1#
b110110100 .
#438
0#
b110110101 .
#439
1#
b110110110 .
#440
0#
b110110111 .
#441
1#
b110111000 .
#442
0#
b110111001 .
#443
1#
b110111010 .
#444
0#
b110111011 .
#445
1#
b110111100 .
#446
0#
b110111101 .
#447
1#
b110111110 .
#448
0#
b110111111 .
#449
1#
b111000000 .
#450
0#
b111000001 .
#451
1#
b111000010 .
#452
0#
b111000011 .
#453
1#
b111000100 .
#454
0#
b111000101 .
#455
1#
b111000110 .
#456
0#
b111000111 .
#457
1#
b111001000 .
#458
0#
b111001001 .
#459
1#
b111001010 .
#460
0#
b111001011 .
#461
1#
b111001100 .
#462
0#
b111001101 .
#463
1#
b111001110 .
#464
0#
b111001111 .
#465
1#
b111010000 .
#466
0#
b111010001 .
#467
1#
b111010010 .
#468
0#
b111010011 .
#469
1#
b111010100 .
#470
0#
b111010101 .
#471
1#
b111010110 .
#472
0#
b111010111 .
#473
1#
b111011000 .
#474
0#
b111011001 .
#475
1#
b111011010 .
#476
0#
b111011011 .
#477
1#
b111011100 .
#478
0#
b111011101 .
#479
1#
b111011110 .
#480
0#
b111011111 .
#481
1#
b111100000 .
#482
0#
b111100001 .
#483
1#
b111100010 .
#484
0#
b111100011 .
#485
1#
b111100100 .
#486
0#
b111100101 .
#487
1#
b111100110 .
#488
0#
b111100111 .
#489
1#
b111101000 .
#490
0#
b111101001 .
#491
1#
b111101010 .
#492
0#
b111101011 .
#493
1#
b111101100 .
#494
0#
b111101101 .
#495
1#
b111101110 .
#496
0#
b111101111 .
#497
1#
b111110000 .
#498
0#
b111110001 .
#499
1#
b111110010 .
#500
0#
b111110011 .
#501
1#
b111110100 .
#502
0#
b111110101 .
#503
1#
b111110110 .
#504
0#
b111110111 .
#505
1#
b111111000 .
#506
0#
b111111001 .
#507
1#
b111111010 .
#508
0#
b111111011 .
#509
1#
b111111100 .
#510
0#
b111111101 .
#511
1#
b111111110 .
#512
0#
b111111111 .
#513
1#
b1000000000 .
#514
0#
b1000000001 .
#515
1#
b1000000010 .
#516
0#
b1000000011 .
#517
1#
b1000000100 .
#518
0#
b1000000101 .
#519
1#
b1000000110 .
#520
0#
b1000000111 .
#521
1#
b1000001000 .
#522
0#
b1000001001 .
#523
1#
b1000001010 .
#524
0#
b1000001011 .
#525
1#
b1000001100 .
#526
0#
b1000001101 .
#527
1#
b1000001110 .
#528
0#
b1000001111 .
#529
1#
b1000010000 .
#530
0#
b1000010001 .
#531
1#
b1000010010 .
#532
0#
b1000010011 .
#533
1#
b1000010100 .
#534
0#
b1000010101 .
#535
1#
b1000010110 .
#536
0#
b1000010111 .
#537
1#
b1000011000 .
#538
0#
b1000011001 .
#539
1#
b1000011010 .
#540
0#
b1000011011 .
#541
1#
b1000011100 .
#542
0#
b1000011101 .
#543
1#
b1000011110 .
#544
0#
b1000011111 .
#545
1#
b1000100000 .
#546
0#
b1000100001 .
#547
1#
b1000100010 .
#548
0#
b1000100011 .
#549
1#
b1000100100 .
#550
0#
b1000100101 .
#551
1#
b1000100110 .
#552
0#
b1000100111 .
#553
1#
b1000101000 .
#554
0#
b1000101001 .
#555
1#
b1000101010 .
#556
0#
b1000101011 .
#557
1#
b1000101100 .
#558
0#
b1000101101 .
#559
1#
b1000101110 .
#560
0#
b1000101111 .
#561
1#
b1000110000 .
#562
0#
b1000110001 .
#563
1#
b1000110010 .
#564
0#
b1000110011 .
#565
1#
b1000110100 .
#566
0#
b1000110101 .
#567
1#
b1000110110 .
#568
0#
b1000110111 .
#569
1#
b1000111000 .
#570
0#
b1000111001 .
#571
1#
b1000111010 .
#572
0#
b1000111011 .
#573
1#
b1000111100 .
#574
0#
b1000111101 .
#575
1#
b1000111110 .
#576
0#
b1000111111 .
#577
1#
b1001000000 .
#578
0#
b1001000001 .
#579
1#
b1001000010 .
#580
0#
b1001000011 .
#581
1#
b1001000100 .
#582
0#
b1001000101 .
#583
1#
b1001000110 .
#584
0#
b1001000111 .
#585
1#
b1001001000 .
#586
0#
b1001001001 .
#587
1#
b1001001010 .
#588
0#
b1001001011 .
#589
1#
b1001001100 .
#590
0#
b1001001101 .
#591
1#
b1001001110 .
#592
0#
b1001001111 .
#593
1#
b1001010000 .
#594
0#
b1001010001 .
#595
1#
b1001010010 .
#596
0#
b1001010011 .
#597
1#
b1001010100 .
#598
0#
b1001010101 .
#599
1#
b1001010110 .
#600
0#
b1001010111 .
#601
1#
b1001011000 .
#602
0#
b1001011001 .
#603
1#
b1001011010 .
#604
0#
b1001011011 .
#605
1#
b1001011100 .
#606
0#
b1001011101 .
#607
1#
b1001011110 .
#608
0#
b1001011111 .
#609
1#
b1001100000 .
#610
0#
b1001100001 .
#611
1#
b1001100010 .
#612
0#
b1001100011 .
#613
1#
b1001100100 .
#614
0#
b1001100101 .
#615
1#
b1001100110 .
#616
0#
b1001100111 .
#617
1#
b1001101000 .
#618
0#
b1001101001 .
#619
1#
b1001101010 .
#620
0#
b1001101011 .
#621
1#
b1001101100 .
#622
0#
b1001101101 .
#623
1#
b1001101110 .
#624
0#
b1001101111 .
#625
1#
b1001110000 .
#626
0#
b1001110001 .
#627
1#
b1001110010 .
#628
0#
b1001110011 .
#629
1#
b1001110100 .
#630
0#
b1001110101 .
#631
1#
b1001110110 .
#632
0#
b1001110111 .
#633
1#
b1001111000 .
#634
0#
b1001111001 .
#635
1#
b1001111010 .
#636
0#
b1001111011 .
#637
1#
b1001111100 .
#638
0#
b1001111101 .
#639
1#
b1001111110 .
#640
0#
b1001111111 .
#641
1#
b1010000000 .
#642
0#
b1010000001 .
#643
1#
b1010000010 .
#644
0#
b1010000011 .
#645
1#
b1010000100 .
#646
0#
b1010000101 .
#647
1#
b1010000110 .
#648
0#
b1010000111 .
#649
1#
b1010001000 .
#650
0#
b1010001001 .
#651
1#
b1010001010 .
#652
0#
b1010001011 .
#653
1#
b1010001100 .
#654
0#
b1010001101 .
#655
1#
b1010001110 .
#656
0#
b1010001111 .
#657
1#
b1010010000 .
#658
0#
b1010010001 .
#659
1#
b1010010010 .
#660
0#
b1010010011 .
#661
1#
b1010010100 .
#662
0#
b1010010101 .
#663
1#
b1010010110 .
#664
0#
b1010010111 .
#665
1#
b1010011000 .
#666
0#
b1010011001 .
#667
1#
b1010011010 .
#668
0#
b1010011011 .
#669
1#
b1010011100 .
#670
0#
b1010011101 .
#671
1#
b1010011110 .
#672
0#
b1010011111 .
#673
1#
b1010100000 .
#674
0#
b1010100001 .
#675
1#
b1010100010 .
#676
0#
b1010100011 .
#677
1#
b1010100100 .
#678
0#
b1010100101 .
#679
1#
b1010100110 .
#680
0#
b1010100111 .
#681
1#
b1010101000 .
#682
0#
b1010101001 .
#683
1#
b1010101010 .
#684
0#
b1010101011 .
#685
1#
b1010101100 .
#686
0#
b1010101101 .
#687
1#
b1010101110 .
#688
0#
b1010101111 .
#689
1#
b1010110000 .
#690
0#
b1010110001 .
#691
1#
b1010110010 .
#692
0#
b1010110011 .
#693
1#
b1010110100 .
#694
0#
b1010110101 .
#695
1#
b1010110110 .
#696
0#
b1010110111 .
#697
1#
b1010111000 .
#698
0#
b1010111001 .
#699
1#
b1010111010 .
#700
0#
b1010111011 .
#701
1#
b1010111100 .
#702
0#
b1010111101 .
#703
1#
b1010111110 .
#704
0#
b1010111111 .
#705
1#
b1011000000 .
#706
0#
b1011000001 .
#707
1#
b1011000010 .
#708
0#
b1011000011 .
#709
1#
b1011000100 .
#710
0#
b1011000101 .
#711
1#
b1011000110 .
#712
0#
b1011000111 .
#713
1#
b1011001000 .
#714
0#
b1011001001 .
#715
1#
b1011001010 .
#716
0#
b1011001011 .
#717
1#
b1011001100 .
#718
0#
b1011001101 .
#719
1#
b1011001110 .
#720
0#
b1011001111 .
#721
1#
b1011010000 .
#722
0#
b1011010001 .
#723
1#
b1011010010 .
#724
0#
b1011010011 .
#725
1#
b1011010100 .
#726
0#
b1011010101 .
#727
1#
b1011010110 .
#728
0#
b1011010111 .
#729
1#
b1011011000 .
#730
0#
b1011011001 .
#731
1#
b1011011010 .
#732
0#
b1011011011 .
#733
1#
b1011011100 .
#734
0#
b1011011101 .
#735
1#
b1011011110 .
#736
0#
b1011011111 .
#737
1#
b1011100000 .
#738
0#
b1011100001 .
#739
1#
b1011100010 .
#740
0#
b1011100011 .
#741
1#
b1011100100 .
#742
0#
b1011100101 .
#743
1#
b1011100110 .
#744
0#
b1011100111 .
#745
1#
b1011101000 .
#746
0#
b1011101001 .
#747
1#
b1011101010 .
#748
0#
b1011101011 .
#749
1#
b1011101100 .
#750
0#
b1011101101 .
#751
1#
b1011101110 .
#752
0#
b1011101111 .
#753
1#
b1011110000 .
#754
0#
b1011110001 .
#755
1#
b1011110010 .
#756
0#
b1011110011 .
#757
1#
b1011110100 .
#758
0#
b1011110101 .
#759
1#
b1011110110 .
#760
0#
b1011110111 .
#761
1#
b1011111000 .
#762
0#
b1011111001 .
#763
1#
b1011111010 .
#764
0#
b1011111011 .
#765
1#
b1011111100 .
#766
0#
b1011111101 .
#767
1#
b1011111110 .
#768
0#
b1011111111 .
#769
1#
b1100000000 .
#770
0#
b1100000001 .
#771
1#
b1100000010 .
#772
0#
b1100000011 .
#773
1#
b1100000100 .
#774
0#
b1100000101 .
#775
1#
b1100000110 .
#776
0#
b1100000111 .
#777
1#
b1100001000 .
#778
0#
b1100001001 .
#779
1#
b1100001010 .
#780
0#
b1100001011 .
#781
1#
b1100001100 .
#782
0#
b1100001101 .
#783
1#
b1100001110 .
#784
0#
b1100001111 .
#785
1#
b1100010000 .
#786
0#
b1100010001 .
#787
1#
b1100010010 .
#788
0#
b1100010011 .
#789
1#
b1100010100 .
#790
0#
b1100010101 .
#791
1#
b1100010110 .
#792
0#
b1100010111 .
#793
1#
b1100011000 .
#794
0#
b1100011001 .
#795
1#
b1100011010 .
#796
0#
b1100011011 .
#797
1#
b1100011100 .
#798
0#
b1100011101 .
#799
1#
b1100011110 .
#800
0#
b1100011111 .
#801
1#
b1100100000 .
#802
0#
b1100100001 .
#803
1#
b1100100010 .
#804
0#
b1100100011 .
#805
1#
b1100100100 .
#806
0#
b1100100101 .
#807
1#
b1100100110 .
#808
0#
b1100100111 .
#809
1#
b1100101000 .
#810
0#
b1100101001 .
#811
1#
b1100101010 .
#812
0#
b1100101011 .
#813
1#
b1100101100 .
#814
0#
b1100101101 .
#815
1#
b1100101110 .
#816
0#
b1100101111 .
#817
1#
b1100110000 .
#818
0#
b1100110001 .
#819
1#
b1100110010 .
#820
0#
b1100110011 .
#821
1#
b1100110100 .
#822
0#
b1100110101 .
#823
1#
b1100110110 .
#824
0#
b1100110111 .
#825
1#
b1100111000 .
#826
0#
b1100111001 .
#827
1#
b1100111010 .
#828
0#
b1100111011 .
#829
1#
b1100111100 .
#830
0#
b1100111101 .
#831
1#
b1100111110 .
#832
0#
b1100111111 .
#833
1#
b1101000000 .
#834
0#
b1101000001 .
#835
1#
b1101000010 .
#836
0#
b1101000011 .
#837
1#
b1101000100 .
#838
0#
b1101000101 .
#839
1#
b1101000110 .
#840
0#
b1101000111 .
#841
1#
b1101001000 .
#842
0#
b1101001001 .
#843
1#
b1101001010 .
#844
0#
b1101001011 .
