core/riscv/riscv_multiplier.v
//-----------------------------------------------------------------
//                         RISC-V Core
//                            V1.0.1
//                     Ultra-Embedded.com
//                     Copyright 2014-2019
//
//                   admin@ultra-embedded.com
//
//                       License: BSD
//-----------------------------------------------------------------
//
// Copyright (c) 2014-2019, Ultra-Embedded.com
// All rights reserved.
// 
// Redistribution and use in source and binary forms, with or without
// modification, are permitted provided that the following conditions 
// are met:
//   - Redistributions of source code must retain the above copyright
//     notice, this list of conditions and the following disclaimer.
//   - Redistributions in binary form must reproduce the above copyright
//     notice, this list of conditions and the following disclaimer 
//     in the documentation and/or other materials provided with the 
//     distribution.
//   - Neither the name of the author nor the names of its contributors 
//     may be used to endorse or promote products derived from this 
//     software without specific prior written permission.
// 
// THIS SOFTWARE IS PROVIDED BY THE COPYRIGHT HOLDERS AND CONTRIBUTORS 
// "AS IS" AND ANY EXPRESS OR IMPLIED WARRANTIES, INCLUDING, BUT NOT 
// LIMITED TO, THE IMPLIED WARRANTIES OF MERCHANTABILITY AND FITNESS FOR 
// A PARTICULAR PURPOSE ARE DISCLAIMED. IN NO EVENT SHALL THE AUTHOR BE 
// LIABLE FOR ANY DIRECT, INDIRECT, INCIDENTAL, SPECIAL, EXEMPLARY, OR 
// CONSEQUENTIAL DAMAGES (INCLUDING, BUT NOT LIMITED TO, PROCUREMENT OF 
// SUBSTITUTE GOODS OR SERVICES; LOSS OF USE, DATA, OR PROFITS; OR 
// BUSINESS INTERRUPTION) HOWEVER CAUSED AND ON ANY THEORY OF 
// LIABILITY, WHETHER IN CONTRACT, STRICT LIABILITY, OR TORT
// (INCLUDING NEGLIGENCE OR OTHERWISE) ARISING IN ANY WAY OUT OF 
// THE USE OF THIS SOFTWARE, EVEN IF ADVISED OF THE POSSIBILITY OF 
// SUCH DAMAGE.
//-----------------------------------------------------------------

module riscv_multiplier
(
    // Inputs
     input           clk_i
    ,input           rst_i
    ,input           opcode_valid_i //unused
    ,input  [ 31:0]  opcode_opcode_i
    ,input  [ 31:0]  opcode_pc_i //unused
    ,input           opcode_invalid_i //unused
    ,input  [  4:0]  opcode_rd_idx_i //unused
    ,input  [  4:0]  opcode_ra_idx_i //unused
    ,input  [  4:0]  opcode_rb_idx_i //unused
    ,input  [ 31:0]  opcode_ra_operand_i
    ,input  [ 31:0]  opcode_rb_operand_i
    ,input           hold_i

    // Outputs
    ,output [ 31:0]  writeback_value_o
);



//-----------------------------------------------------------------
// Includes
//-----------------------------------------------------------------
`include "riscv_defs.v"

localparam MULT_STAGES = 2; // 2 or 3

//-------------------------------------------------------------
// Multiplier
//-------------------------------------------------------------
// Stage 1

(*keep*) reg mult_sel;
(*keep*) reg [31:0] a_low;
(*keep*) reg [31:0] a_high;
(*keep*) reg [31:0] b_low;
(*keep*) reg [31:0] b_high;

always @(posedge clk_i or posedge rst_i) begin
    if (rst_i) begin 
        mult_sel <= 0;
        a_low <= 32'b0;
        a_high <= 32'b0;
        b_low <= 32'b0;
        b_high <= 32'b0;
    end
    else if (!hold_i) begin
        a_low <= opcode_ra_operand_i;
        b_low <= opcode_rb_operand_i;
        a_high <= 32'b0;
        b_high <= 32'b0;
        mult_sel <= 0;
        if ((opcode_opcode_i & `INST_MUL_MASK) == `INST_MUL) begin
            mult_sel <= 1;
        end else if ((opcode_opcode_i & `INST_MULH_MASK) == `INST_MULH) begin
            a_high <= ($signed(opcode_ra_operand_i) < 0) ? 32'hffff_ffff:32'h0; 
            b_high <= ($signed(opcode_rb_operand_i) < 0) ? 32'hffff_ffff:32'h0;
        end else if ((opcode_opcode_i & `INST_MULHSU_MASK) == `INST_MULHSU) begin
            a_high <= ($signed(opcode_ra_operand_i) < 0) ? 32'hffff_ffff:32'h0; 
        end else if ((opcode_opcode_i & `INST_MULHU_MASK) == `INST_MULHU) begin
            ;
        end
    end
end

// Stage 2

reg [31:0] result_e2_q;
reg [31:0] result_e3_q;
wire [64:0] mult_result_w;
assign mult_result_w = {a_high, a_low} * {b_high, b_low};
always @(posedge clk_i or posedge rst_i) begin
    if (rst_i)
        result_e2_q <= 32'b0;
    else if (~hold_i)
        result_e2_q <= mult_sel ? mult_result_w[31:0] : mult_result_w[63:32];
end

// Stage 3

always @(posedge clk_i or posedge rst_i)
if (rst_i)
    result_e3_q <= 32'b0;
else if (~hold_i)
    result_e3_q <= result_e2_q;

// End of stages

assign writeback_value_o  = (MULT_STAGES == 3) ? result_e3_q : result_e2_q;


endmodule

testbench/multiplier/tb.v
`include "../../core/riscv/riscv_defs.v"
`include "../../core/riscv/riscv_multiplier.v"

module tb;
	reg clk_i;
	reg rst_i;
	reg opcode_valid_i;
	reg [31:0]opcode_opcode_i;
	reg [31:0]opcode_pc_i;
	reg opcode_invalid_i;
	reg [4:0]opcode_rd_idx_i;
	reg [4:0]opcode_ra_idx_i;
	reg [4:0]opcode_rb_idx_i;
	reg [31:0]opcode_ra_operand_i;
	reg [31:0]opcode_rb_operand_i;
	reg hold_i;

	wire [31:0] writeback_value_o;

	riscv_multiplier dut (
		.clk_i(clk_i),
		.rst_i(rst_i),
		.opcode_valid_i(opcode_valid_i),
		.opcode_opcode_i(opcode_opcode_i),
		.opcode_pc_i(opcode_pc_i),
		.opcode_invalid_i(opcode_invalid_i),
		.opcode_rd_idx_i(opcode_rd_idx_i),
		.opcode_ra_idx_i(opcode_ra_idx_i),
		.opcode_rb_idx_i(opcode_rb_idx_i),
		.opcode_ra_operand_i(opcode_ra_operand_i),
		.opcode_rb_operand_i(opcode_rb_operand_i),
		.hold_i(hold_i),
		.writeback_value_o(writeback_value_o)
	);

	initial begin
		$dumpfile("tb.vcd");
		$dumpvars(1, tb);

		clk_i = 0;
		rst_i = 0;
		opcode_valid_i = 0;
		opcode_opcode_i = 0;
		opcode_pc_i = 0;
		opcode_invalid_i = 0;
		opcode_rd_idx_i = 0;
		opcode_ra_idx_i = 0;
		opcode_rb_idx_i = 0;
		opcode_ra_operand_i = 0;
		opcode_rb_operand_i = 0;
		hold_i = 0;
		#1;

		// TEST PAIR 0
		clk_i = 0;
		opcode_ra_operand_i = 3;
		opcode_rb_operand_i = 4;
		opcode_opcode_i= `INST_MUL;
		#1;
		clk_i = 1;
		#1;

		clk_i = 0;
		opcode_opcode_i= `INST_MULH;
		#1;
		clk_i = 1;
		#1;

		clk_i = 0;
		opcode_opcode_i= `INST_MULHSU;
		#1;
		clk_i = 1;
		#1;

		clk_i = 0;
		opcode_opcode_i= `INST_MULHU;
		#1;
		clk_i = 1;
		#1;

		// TEST PAIR 1
		clk_i = 0;
		opcode_ra_operand_i = -50;
		opcode_rb_operand_i = 7;
		opcode_opcode_i= `INST_MUL;
		#1;
		clk_i = 1;
		#1;

		clk_i = 0;
		opcode_opcode_i= `INST_MULH;
		#1;
		clk_i = 1;
		#1;

		clk_i = 0;
		opcode_opcode_i= `INST_MULHSU;
		#1;
		clk_i = 1;
		#1;

		clk_i = 0;
		opcode_opcode_i= `INST_MULHU;
		#1;
		clk_i = 1;
		#1;

		// TEST PAIR 2
		clk_i = 0;
		opcode_ra_operand_i = 800_000_000;
		opcode_rb_operand_i = -50_000;
		opcode_opcode_i= `INST_MUL;
		#1;
		clk_i = 1;
		#1;

		clk_i = 0;
		opcode_opcode_i= `INST_MULH;
		#1;
		clk_i = 1;
		#1;

		clk_i = 0;
		opcode_opcode_i= `INST_MULHSU;
		#1;
		clk_i = 1;
		#1;

		clk_i = 0;
		opcode_opcode_i= `INST_MULHU;
		#1;
		clk_i = 1;
		#1;

		// Same test with hold
		// Same test with hold
		// TEST PAIR 1
		clk_i = 0;
		opcode_ra_operand_i = -50;
		opcode_rb_operand_i = 7;
		opcode_opcode_i= `INST_MUL;
		hold_i = 1;
		#1;
		clk_i = 1;
		#1;

		clk_i = 0;
		opcode_opcode_i= `INST_MULH;
		#1;
		clk_i = 1;
		#1;

		clk_i = 0;
		opcode_opcode_i= `INST_MULHSU;
		#1;
		clk_i = 1;
		#1;

		clk_i = 0;
		opcode_opcode_i= `INST_MULHU;
		#1;
		clk_i = 1;
		#1;

		// TEST PAIR 2
		clk_i = 0;
		opcode_ra_operand_i = 800_000_000;
		opcode_rb_operand_i = -50_000;
		opcode_opcode_i= `INST_MUL;
		#1;
		clk_i = 1;
		#1;

		clk_i = 0;
		opcode_opcode_i= `INST_MULH;
		#1;
		clk_i = 1;
		#1;

		clk_i = 0;
		opcode_opcode_i= `INST_MULHSU;
		#1;
		clk_i = 1;
		#1;

		clk_i = 0;
		opcode_opcode_i= `INST_MULHU;
		#1;
		clk_i = 1;
		#1;

		// Same test with reset
		// Same test with reset
		// TEST PAIR 1
		clk_i = 0;
		opcode_ra_operand_i = -50;
		opcode_rb_operand_i = 7;
		opcode_opcode_i= `INST_MUL;
		hold_i = 0;
		#1;
		clk_i = 1;
		#1;

		clk_i = 0;
		opcode_opcode_i= `INST_MULH;
		#1;
		clk_i = 1;
		#1;

		clk_i = 0;
		opcode_opcode_i= `INST_MULHSU;
		#1;
		clk_i = 1;
		#1;

		clk_i = 0;
		opcode_opcode_i= `INST_MULHU;
		#1;
		clk_i = 1;
		#1;

		// TEST PAIR 2
		clk_i = 0;
		opcode_ra_operand_i = 800_000_000;
		opcode_rb_operand_i = -50_000;
		opcode_opcode_i= `INST_MUL;
		rst_i = 1;
		#1;
		clk_i = 1;
		#1;

		clk_i = 0;
		opcode_opcode_i= `INST_MULH;
		#1;
		clk_i = 1;
		#1;

		clk_i = 0;
		opcode_opcode_i= `INST_MULHSU;
		#1;
		clk_i = 1;
		#1;

		clk_i = 0;
		opcode_opcode_i= `INST_MULHU;
		#1;
		clk_i = 1;
		#1;

		$finish;
	end
endmodule

testbench/multiplier/multiplier_tb.vcd
$date
	Sun Nov  2 01:54:38 2025
$end
$version
	Icarus Verilog
$end
$timescale
	1s
$end
$scope module tb $end
$var wire 32 ! writeback_value_o [31:0] $end
$var reg 1 " clk_i $end
$var reg 1 # hold_i $end
$var reg 1 $ opcode_invalid_i $end
$var reg 32 % opcode_opcode_i [31:0] $end
$var reg 32 & opcode_pc_i [31:0] $end
$var reg 5 ' opcode_ra_idx_i [4:0] $end
$var reg 32 ( opcode_ra_operand_i [31:0] $end
$var reg 5 ) opcode_rb_idx_i [4:0] $end
$var reg 32 * opcode_rb_operand_i [31:0] $end
$var reg 5 + opcode_rd_idx_i [4:0] $end
$var reg 1 , opcode_valid_i $end
$var reg 1 - rst_i $end
$scope module dut $end
$var wire 1 " clk_i $end
$var wire 1 # hold_i $end
$var wire 1 $ opcode_invalid_i $end
$var wire 32 . opcode_opcode_i [31:0] $end
$var wire 32 / opcode_pc_i [31:0] $end
$var wire 5 0 opcode_ra_idx_i [4:0] $end
$var wire 32 1 opcode_ra_operand_i [31:0] $end
$var wire 5 2 opcode_rb_idx_i [4:0] $end
$var wire 32 3 opcode_rb_operand_i [31:0] $end
$var wire 5 4 opcode_rd_idx_i [4:0] $end
$var wire 1 , opcode_valid_i $end
$var wire 1 - rst_i $end
$var wire 32 5 writeback_value_o [31:0] $end
$var wire 65 6 mult_result_w [64:0] $end
$var parameter 32 7 MULT_STAGES $end
$var reg 32 8 a_high [31:0] $end
$var reg 32 9 a_low [31:0] $end
$var reg 32 : b_high [31:0] $end
$var reg 32 ; b_low [31:0] $end
$var reg 1 < mult_sel $end
$var reg 32 = result_e2_q [31:0] $end
$var reg 32 > result_e3_q [31:0] $end
$upscope $end
$upscope $end
$enddefinitions $end
$comment Show the parameter values. $end
$dumpall
b10 7
$end
#0
$dumpvars
bx >
bx =
x<
bx ;
bx :
bx 9
bx 8
bx 6
bx 5
b0 4
b0 3
b0 2
b0 1
b0 0
b0 /
b0 .
0-
0,
b0 +
b0 *
b0 )
b0 (
b0 '
b0 &
b0 %
0$
0#
0"
bx !
$end
#1
b10000000000000000000110011 %
b10000000000000000000110011 .
b100 *
b100 3
b11 (
b11 1
#2
1<
b1100 6
b0 :
b0 8
b100 ;
b11 9
1"
#3
b10000000000001000000110011 %
b10000000000001000000110011 .
0"
#4
b1100 !
b1100 5
b1100 =
0<
1"
#5
b10000000000010000000110011 %
b10000000000010000000110011 .
0"
#6
b0 !
b0 5
b0 =
b1100 >
1"
#7
b10000000000011000000110011 %
b10000000000011000000110011 .
0"
#8
b0 >
1"
#9
b10000000000000000000110011 %
b10000000000000000000110011 .
b111 *
b111 3
b11111111111111111111111111001110 (
b11111111111111111111111111001110 1
0"
#10
1<
b111 ;
b11011111111111111111111111010100010 6
b11111111111111111111111111001110 9
1"
#11
b10000000000001000000110011 %
b10000000000001000000110011 .
0"
#12
b11111111111111111111111010100010 !
b11111111111111111111111010100010 5
b11111111111111111111111010100010 =
b1111111111111111111111111111111111111111111111111111111010100010 6
b11111111111111111111111111111111 8
0<
1"
#13
b10000000000010000000110011 %
b10000000000010000000110011 .
0"
#14
b1111111111111111111111111111111111111111111111111111111010100010 6
b11111111111111111111111111111111 8
b11111111111111111111111111111111 !
b11111111111111111111111111111111 5
b11111111111111111111111111111111 =
b11111111111111111111111010100010 >
1"
#15
b10000000000011000000110011 %
b10000000000011000000110011 .
0"
#16
b11111111111111111111111111111111 >
b11011111111111111111111111010100010 6
b0 8
1"
#17
b10000000000000000000110011 %
b10000000000000000000110011 .
b11111111111111110011110010110000 *
b11111111111111110011110010110000 3
b101111101011110000100000000000 (
b101111101011110000100000000000 1
0"
#18
1<
b11111111111111110011110010110000 ;
b10111110101110111000111001111011000110001101011000000000000000 6
b101111101011110000100000000000 9
b110 !
b110 5
b110 =
1"
#19
b10000000000001000000110011 %
b10000000000001000000110011 .
0"
#20
b110 >
b11000110001101011000000000000000 !
b11000110001101011000000000000000 5
b11000110001101011000000000000000 =
b11111111111111111110110111001111011000110001101011000000000000000 6
b11111111111111111111111111111111 :
0<
1"
#21
b10000000000010000000110011 %
b10000000000010000000110011 .
0"
#22
b10111110101110111000111001111011000110001101011000000000000000 6
b0 :
b11111111111111111101101110011110 !
b11111111111111111101101110011110 5
b11111111111111111101101110011110 =
b11000110001101011000000000000000 >
1"
#23
b10000000000011000000110011 %
b10000000000011000000110011 .
0"
#24
b11111111111111111101101110011110 >
b101111101011101110001110011110 !
b101111101011101110001110011110 5
b101111101011101110001110011110 =
1"
#25
1#
b10000000000000000000110011 %
b10000000000000000000110011 .
b111 *
b111 3
b11111111111111111111111111001110 (
b11111111111111111111111111001110 1
0"
#26
1"
#27
b10000000000001000000110011 %
b10000000000001000000110011 .
0"
#28
1"
#29
b10000000000010000000110011 %
b10000000000010000000110011 .
0"
#30
1"
#31
b10000000000011000000110011 %
b10000000000011000000110011 .
0"
#32
1"
#33
b10000000000000000000110011 %
b10000000000000000000110011 .
b11111111111111110011110010110000 *
b11111111111111110011110010110000 3
b101111101011110000100000000000 (
b101111101011110000100000000000 1
0"
#34
1"
#35
b10000000000001000000110011 %
b10000000000001000000110011 .
0"
#36
1"
#37
b10000000000010000000110011 %
b10000000000010000000110011 .
0"
#38
1"
#39
b10000000000011000000110011 %
b10000000000011000000110011 .
0"
#40
1"
#41
0#
b10000000000000000000110011 %
b10000000000000000000110011 .
b111 *
b111 3
b11111111111111111111111111001110 (
b11111111111111111111111111001110 1
0"
#42
1<
b111 ;
b11011111111111111111111111010100010 6
b11111111111111111111111111001110 9
b101111101011101110001110011110 >
1"
#43
b10000000000001000000110011 %
b10000000000001000000110011 .
0"
#44
b11111111111111111111111010100010 !
b11111111111111111111111010100010 5
b11111111111111111111111010100010 =
b1111111111111111111111111111111111111111111111111111111010100010 6
b11111111111111111111111111111111 8
0<
1"
#45
b10000000000010000000110011 %
b10000000000010000000110011 .
0"
#46
b1111111111111111111111111111111111111111111111111111111010100010 6
b11111111111111111111111111111111 8
b11111111111111111111111111111111 !
b11111111111111111111111111111111 5
b11111111111111111111111111111111 =
b11111111111111111111111010100010 >
1"
#47
b10000000000011000000110011 %
b10000000000011000000110011 .
0"
#48
b11111111111111111111111111111111 >
b11011111111111111111111111010100010 6
b0 8
1"
#49
b0 ;
b0 6
b0 9
b0 !
b0 5
b0 =
b0 >
1-
b10000000000000000000110011 %
b10000000000000000000110011 .
b11111111111111110011110010110000 *
b11111111111111110011110010110000 3
b101111101011110000100000000000 (
b101111101011110000100000000000 1
0"
#50
1"
#51
b10000000000001000000110011 %
b10000000000001000000110011 .
0"
#52
1"
#53
b10000000000010000000110011 %
b10000000000010000000110011 .
0"
#54
1"
#55
b10000000000011000000110011 %
b10000000000011000000110011 .
0"
